{
  "trk": {
    "name": "Star Trek",
    "released_at": "2026-11-13"
  },
  "ttrk": {
    "name": "Star Trek Tokens",
    "released_at": "2026-11-13"
  },
  "trc": {
    "name": "Star Trek Commander",
    "released_at": "2026-11-13"
  },
  "sds": {
    "name": "Stardates",
    "released_at": "2026-11-13"
  },
  "frc": {
    "name": "Reality Fracture Commander",
    "released_at": "2026-10-02"
  },
  "fra": {
    "name": "Reality Fracture",
    "released_at": "2026-10-02"
  },
  "mbc": {
    "name": "Mystery Booster: Commander Edition",
    "released_at": "2026-10-01"
  },
  "hob": {
    "name": "The Hobbit",
    "released_at": "2026-08-14"
  },
  "hoc": {
    "name": "The Hobbit Commander",
    "released_at": "2026-08-14"
  },
  "thob": {
    "name": "The Hobbit Tokens",
    "released_at": "2026-08-14"
  },
  "tmsh": {
    "name": "Marvel Super Heroes Tokens",
    "released_at": "2026-06-26"
  },
  "msh": {
    "name": "Marvel Super Heroes",
    "released_at": "2026-06-26"
  },
  "amsh": {
    "name": "Marvel Super Heroes Art Series",
    "released_at": "2026-06-26"
  },
  "fmsc": {
    "name": "Marvel Super Heroes Jumpstart Front Cards",
    "released_at": "2026-06-26"
  },
  "msc": {
    "name": "Marvel Super Heroes Commander",
    "released_at": "2026-06-26"
  },
  "tmsc": {
    "name": "Marvel Super Heroes Commander Tokens",
    "released_at": "2026-06-26"
  },
  "ysos": {
    "name": "Alchemy: Secrets of Strixhaven",
    "released_at": "2026-05-19"
  },
  "psos": {
    "name": "Secrets of Strixhaven Promos",
    "released_at": "2026-04-24"
  },
  "soa": {
    "name": "Secrets of Strixhaven Mystical Archive",
    "released_at": "2026-04-24"
  },
  "sos": {
    "name": "Secrets of Strixhaven",
    "released_at": "2026-04-24"
  },
  "soc": {
    "name": "Secrets of Strixhaven Commander",
    "released_at": "2026-04-24"
  },
  "tsos": {
    "name": "Secrets of Strixhaven Tokens",
    "released_at": "2026-04-24"
  },
  "tsoc": {
    "name": "Secrets of Strixhaven Commander Tokens",
    "released_at": "2026-04-24"
  },
  "asos": {
    "name": "Secrets of Strixhaven Art Series",
    "released_at": "2026-04-24"
  },
  "pza": {
    "name": "Teenage Mutant Ninja Turtles Source Material",
    "released_at": "2026-03-06"
  },
  "ttmt": {
    "name": "Teenage Mutant Ninja Turtles Tokens",
    "released_at": "2026-03-06"
  },
  "tmc": {
    "name": "Teenage Mutant Ninja Turtles Eternal",
    "released_at": "2026-03-06"
  },
  "tmt": {
    "name": "Teenage Mutant Ninja Turtles",
    "released_at": "2026-03-06"
  },
  "atmt": {
    "name": "Teenage Mutant Ninja Turtles Art Series",
    "released_at": "2026-03-06"
  },
  "ttmc": {
    "name": "Teenage Mutant Ninja Turtles Eternal Tokens",
    "released_at": "2026-03-06"
  },
  "ftmc": {
    "name": "Teenage Mutant Ninja Turtles Eternal Front Cards",
    "released_at": "2026-03-06"
  },
  "pl26": {
    "name": "Year of the Horse 2026",
    "released_at": "2026-02-17"
  },
  "yecl": {
    "name": "Alchemy: Lorwyn Eclipsed",
    "released_at": "2026-02-03"
  },
  "pecl": {
    "name": "Lorwyn Eclipsed Promos",
    "released_at": "2026-01-23"
  },
  "ecl": {
    "name": "Lorwyn Eclipsed",
    "released_at": "2026-01-23"
  },
  "tecl": {
    "name": "Lorwyn Eclipsed Tokens",
    "released_at": "2026-01-23"
  },
  "aecl": {
    "name": "Lorwyn Eclipsed Art Series",
    "released_at": "2026-01-23"
  },
  "tecc": {
    "name": "Lorwyn Eclipsed Commander Tokens",
    "released_at": "2026-01-23"
  },
  "ecc": {
    "name": "Lorwyn Eclipsed Commander",
    "released_at": "2026-01-23"
  },
  "pw26": {
    "name": "Wizards Play Network 2026",
    "released_at": "2026-01-01"
  },
  "pf26": {
    "name": "MagicFest 2026",
    "released_at": "2026-01-01"
  },
  "afic": {
    "name": "Final Fantasy Scene Box",
    "released_at": "2025-12-05"
  },
  "ptla": {
    "name": "Avatar: The Last Airbender Promos",
    "released_at": "2025-11-21"
  },
  "atle": {
    "name": "Avatar: the Last Airbender Eternal Art Series",
    "released_at": "2025-11-21"
  },
  "ttle": {
    "name": "Avatar: The Last Airbender Eternal Tokens",
    "released_at": "2025-11-21"
  },
  "ttla": {
    "name": "Avatar: The Last Airbender Tokens",
    "released_at": "2025-11-21"
  },
  "atla": {
    "name": "Avatar: the Last Airbender Art Series",
    "released_at": "2025-11-21"
  },
  "jtla": {
    "name": "Avatar: The Last Airbender Jumpstart Front Cards",
    "released_at": "2025-11-21"
  },
  "tle": {
    "name": "Avatar: The Last Airbender Eternal",
    "released_at": "2025-11-21"
  },
  "tla": {
    "name": "Avatar: The Last Airbender",
    "released_at": "2025-11-21"
  },
  "ftla": {
    "name": "Avatar: The Last Airbender Beginner Box Front Cards",
    "released_at": "2025-11-21"
  },
  "lmar": {
    "name": "Marvel Legends Series Inserts",
    "released_at": "2025-09-30"
  },
  "pspm": {
    "name": "Marvel's Spider-Man Promos",
    "released_at": "2025-09-26"
  },
  "aspm": {
    "name": "Marvel's Spider-Man Art Series",
    "released_at": "2025-09-26"
  },
  "tspm": {
    "name": "Marvel's Spider-Man Tokens",
    "released_at": "2025-09-26"
  },
  "spe": {
    "name": "Marvel's Spider-Man Eternal",
    "released_at": "2025-09-26"
  },
  "spm": {
    "name": "Marvel's Spider-Man",
    "released_at": "2025-09-26"
  },
  "mar": {
    "name": "Marvel Universe",
    "released_at": "2025-09-26"
  },
  "aa4": {
    "name": "Arena Anthology 4",
    "released_at": "2025-09-23"
  },
  "aa3": {
    "name": "Arena Anthology 3",
    "released_at": "2025-09-23"
  },
  "omb": {
    "name": "Through the Omenpaths Bonus Sheet",
    "released_at": "2025-09-23"
  },
  "om1": {
    "name": "Through the Omenpaths",
    "released_at": "2025-09-23"
  },
  "ph23": {
    "name": "2023 Heroes of the Realm",
    "released_at": "2025-08-24"
  },
  "aa2": {
    "name": "Arena Anthology 2",
    "released_at": "2025-08-19"
  },
  "yeoe": {
    "name": "Alchemy: Edge of Eternities",
    "released_at": "2025-08-19"
  },
  "aa1": {
    "name": "Arena Anthology 1",
    "released_at": "2025-08-19"
  },
  "aeoe": {
    "name": "Edge of Eternities Art Series",
    "released_at": "2025-08-01"
  },
  "peoe": {
    "name": "Edge of Eternities Promos",
    "released_at": "2025-08-01"
  },
  "pbig": {
    "name": "The Big Score Promos",
    "released_at": "2025-08-01"
  },
  "teoc": {
    "name": "Edge of Eternities Commander Tokens",
    "released_at": "2025-08-01"
  },
  "teoe": {
    "name": "Edge of Eternities Tokens",
    "released_at": "2025-08-01"
  },
  "eoe": {
    "name": "Edge of Eternities",
    "released_at": "2025-08-01"
  },
  "eos": {
    "name": "Edge of Eternities: Stellar Sights",
    "released_at": "2025-08-01"
  },
  "eoc": {
    "name": "Edge of Eternities Commander",
    "released_at": "2025-08-01"
  },
  "tfin": {
    "name": "Final Fantasy Tokens",
    "released_at": "2025-06-13"
  },
  "rfin": {
    "name": "Final Fantasy Regional Promos",
    "released_at": "2025-06-13"
  },
  "afin": {
    "name": "Final Fantasy Art Series",
    "released_at": "2025-06-13"
  },
  "fic": {
    "name": "Final Fantasy Commander",
    "released_at": "2025-06-13"
  },
  "tfic": {
    "name": "Final Fantasy Commander Tokens",
    "released_at": "2025-06-13"
  },
  "pfin": {
    "name": "Final Fantasy Promos",
    "released_at": "2025-06-13"
  },
  "fca": {
    "name": "Final Fantasy: Through the Ages",
    "released_at": "2025-06-13"
  },
  "pss5": {
    "name": "FIN Standard Showdown",
    "released_at": "2025-06-13"
  },
  "wfin": {
    "name": "FIN Asia WPN Promo Tokens",
    "released_at": "2025-06-13"
  },
  "fin": {
    "name": "Final Fantasy",
    "released_at": "2025-06-13"
  },
  "pa1": {
    "name": "Pioneer Anthology 1",
    "released_at": "2025-05-05"
  },
  "ytdm": {
    "name": "Alchemy: Tarkir",
    "released_at": "2025-04-29"
  },
  "ttdm": {
    "name": "Tarkir: Dragonstorm Tokens",
    "released_at": "2025-04-11"
  },
  "ptdm": {
    "name": "Tarkir: Dragonstorm Promos",
    "released_at": "2025-04-11"
  },
  "atdm": {
    "name": "Tarkir: Dragonstorm Art Series",
    "released_at": "2025-04-11"
  },
  "ttdc": {
    "name": "Tarkir: Dragonstorm Commander Tokens",
    "released_at": "2025-04-11"
  },
  "tdc": {
    "name": "Tarkir: Dragonstorm Commander",
    "released_at": "2025-04-11"
  },
  "tdm": {
    "name": "Tarkir: Dragonstorm",
    "released_at": "2025-04-11"
  },
  "plg25": {
    "name": "Love Your LGS 2025",
    "released_at": "2025-03-26"
  },
  "ydft": {
    "name": "Alchemy: Aetherdrift",
    "released_at": "2025-03-04"
  },
  "pssc": {
    "name": "Secret Lair Showcase Planes",
    "released_at": "2025-02-21"
  },
  "adft": {
    "name": "Aetherdrift Art Series",
    "released_at": "2025-02-14"
  },
  "pdft": {
    "name": "Aetherdrift Promos",
    "released_at": "2025-02-14"
  },
  "pl25": {
    "name": "Year of the Snake 2025",
    "released_at": "2025-02-14"
  },
  "drc": {
    "name": "Aetherdrift Commander",
    "released_at": "2025-02-14"
  },
  "dft": {
    "name": "Aetherdrift",
    "released_at": "2025-02-14"
  },
  "tdft": {
    "name": "Aetherdrift Tokens",
    "released_at": "2025-02-14"
  },
  "tdrc": {
    "name": "Aetherdrift Commander Tokens",
    "released_at": "2025-02-14"
  },
  "pjsc": {
    "name": "Japan Standard Cup",
    "released_at": "2025-02-09"
  },
  "ainr": {
    "name": "Innistrad Remastered Art Series",
    "released_at": "2025-01-24"
  },
  "tinr": {
    "name": "Innistrad Remastered Tokens",
    "released_at": "2025-01-24"
  },
  "inr": {
    "name": "Innistrad Remastered",
    "released_at": "2025-01-24"
  },
  "pspl": {
    "name": "Spotlight Series",
    "released_at": "2025-01-03"
  },
  "pw25": {
    "name": "Wizards Play Network 2025",
    "released_at": "2025-01-01"
  },
  "pf25": {
    "name": "MagicFest 2025",
    "released_at": "2025-01-01"
  },
  "pio": {
    "name": "Pioneer Masters",
    "released_at": "2024-12-10"
  },
  "afdn": {
    "name": "Foundations Art Series",
    "released_at": "2024-11-15"
  },
  "pfdn": {
    "name": "Foundations Promos",
    "released_at": "2024-11-15"
  },
  "ffdn": {
    "name": "Foundations Front Cards",
    "released_at": "2024-11-15"
  },
  "fj25": {
    "name": "Foundations Jumpstart Front Cards",
    "released_at": "2024-11-15"
  },
  "fdc": {
    "name": "Foundations Commander",
    "released_at": "2024-11-15"
  },
  "fdn": {
    "name": "Foundations",
    "released_at": "2024-11-15"
  },
  "tfdn": {
    "name": "Foundations Tokens",
    "released_at": "2024-11-15"
  },
  "j25": {
    "name": "Foundations Jumpstart",
    "released_at": "2024-11-15"
  },
  "pltc": {
    "name": "Tales of Middle-earth Deluxe Commander Kit",
    "released_at": "2024-10-16"
  },
  "ydsk": {
    "name": "Alchemy: Duskmourn",
    "released_at": "2024-10-15"
  },
  "dsk": {
    "name": "Duskmourn: House of Horror",
    "released_at": "2024-09-27"
  },
  "pdsk": {
    "name": "Duskmourn: House of Horror Promos",
    "released_at": "2024-09-27"
  },
  "tdsk": {
    "name": "Duskmourn: House of Horror Tokens",
    "released_at": "2024-09-27"
  },
  "dsc": {
    "name": "Duskmourn: House of Horror Commander",
    "released_at": "2024-09-27"
  },
  "tdsc": {
    "name": "Duskmourn Commander Tokens",
    "released_at": "2024-09-27"
  },
  "adsk": {
    "name": "Duskmourn: House of Horror Art Series",
    "released_at": "2024-09-27"
  },
  "yblb": {
    "name": "Alchemy: Bloomburrow",
    "released_at": "2024-08-20"
  },
  "plg24": {
    "name": "Love Your LGS 2024",
    "released_at": "2024-08-06"
  },
  "tblb": {
    "name": "Bloomburrow Tokens",
    "released_at": "2024-08-02"
  },
  "pblb": {
    "name": "Bloomburrow Promos",
    "released_at": "2024-08-02"
  },
  "tblc": {
    "name": "Bloomburrow Commander Tokens",
    "released_at": "2024-08-02"
  },
  "ablb": {
    "name": "Bloomburrow Art Series",
    "released_at": "2024-08-02"
  },
  "blb": {
    "name": "Bloomburrow",
    "released_at": "2024-08-02"
  },
  "pcbb": {
    "name": "Cowboy Bebop",
    "released_at": "2024-08-02"
  },
  "blc": {
    "name": "Bloomburrow Commander",
    "released_at": "2024-08-02"
  },
  "mb2": {
    "name": "Mystery Booster 2",
    "released_at": "2024-08-02"
  },
  "macr": {
    "name": "Assassin's Creed Minigames",
    "released_at": "2024-07-05"
  },
  "aacr": {
    "name": "Assassin's Creed Art Series",
    "released_at": "2024-07-05"
  },
  "tacr": {
    "name": "Assassin's Creed Tokens",
    "released_at": "2024-07-05"
  },
  "acr": {
    "name": "Assassin's Creed",
    "released_at": "2024-07-05"
  },
  "pmh3": {
    "name": "Modern Horizons 3 Promos",
    "released_at": "2024-06-14"
  },
  "smh3": {
    "name": "Modern Horizons 3 Substitute Cards",
    "released_at": "2024-06-14"
  },
  "tmh3": {
    "name": "Modern Horizons 3 Tokens",
    "released_at": "2024-06-14"
  },
  "amh3": {
    "name": "Modern Horizons 3 Art Series",
    "released_at": "2024-06-14"
  },
  "h2r": {
    "name": "Modern Horizons 2 Timeshifts",
    "released_at": "2024-06-14"
  },
  "mh3": {
    "name": "Modern Horizons 3",
    "released_at": "2024-06-14"
  },
  "m3c": {
    "name": "Modern Horizons 3 Commander",
    "released_at": "2024-06-14"
  },
  "tm3c": {
    "name": "Modern Horizons 3 Commander Tokens",
    "released_at": "2024-06-14"
  },
  "yotj": {
    "name": "Alchemy: Outlaws of Thunder Junction",
    "released_at": "2024-05-07"
  },
  "potj": {
    "name": "Outlaws of Thunder Junction Promos",
    "released_at": "2024-04-19"
  },
  "totj": {
    "name": "Outlaws of Thunder Junction Tokens",
    "released_at": "2024-04-19"
  },
  "aotj": {
    "name": "Outlaws of Thunder Junction Art Series",
    "released_at": "2024-04-19"
  },
  "big": {
    "name": "The Big Score",
    "released_at": "2024-04-19"
  },
  "tbig": {
    "name": "The Big Score Tokens",
    "released_at": "2024-04-19"
  },
  "otc": {
    "name": "Outlaws of Thunder Junction Commander",
    "released_at": "2024-04-19"
  },
  "totp": {
    "name": "Breaking News Tokens",
    "released_at": "2024-04-19"
  },
  "totc": {
    "name": "Outlaws of Thunder Junction Commander Tokens",
    "released_at": "2024-04-19"
  },
  "otj": {
    "name": "Outlaws of Thunder Junction",
    "released_at": "2024-04-19"
  },
  "otp": {
    "name": "Breaking News",
    "released_at": "2024-04-19"
  },
  "pip": {
    "name": "Fallout",
    "released_at": "2024-03-08"
  },
  "tpip": {
    "name": "Fallout Tokens",
    "released_at": "2024-03-08"
  },
  "ymkm": {
    "name": "Alchemy: Murders at Karlov Manor ",
    "released_at": "2024-03-05"
  },
  "punk": {
    "name": "Black Lotus Unknown Planechase",
    "released_at": "2024-02-24"
  },
  "clu": {
    "name": "Ravnica: Clue Edition",
    "released_at": "2024-02-23"
  },
  "fclu": {
    "name": "Ravnica: Clue Edition Front Cards",
    "released_at": "2024-02-23"
  },
  "pss4": {
    "name": "MKM Standard Showdown",
    "released_at": "2024-02-10"
  },
  "tmkm": {
    "name": "Murders at Karlov Manor Tokens",
    "released_at": "2024-02-09"
  },
  "amkm": {
    "name": "Murders at Karlov Manor Art Series",
    "released_at": "2024-02-09"
  },
  "pmkm": {
    "name": "Murders at Karlov Manor Promos",
    "released_at": "2024-02-09"
  },
  "tmkc": {
    "name": "Murders at Karlov Manor Commander Tokens",
    "released_at": "2024-02-09"
  },
  "mkm": {
    "name": "Murders at Karlov Manor",
    "released_at": "2024-02-09"
  },
  "mkc": {
    "name": "Murders at Karlov Manor Commander",
    "released_at": "2024-02-09"
  },
  "wmkm": {
    "name": "MKM Japanese Promo Tokens",
    "released_at": "2024-02-09"
  },
  "pl24": {
    "name": "Year of the Dragon 2024",
    "released_at": "2024-02-08"
  },
  "rvr": {
    "name": "Ravnica Remastered",
    "released_at": "2024-01-12"
  },
  "trvr": {
    "name": "Ravnica Remastered Tokens",
    "released_at": "2024-01-12"
  },
  "pw24": {
    "name": "Wizards Play Network 2024",
    "released_at": "2024-01-01"
  },
  "pf24": {
    "name": "MagicFest 2024",
    "released_at": "2024-01-01"
  },
  "ylci": {
    "name": "Alchemy: Ixalan",
    "released_at": "2023-12-05"
  },
  "spg": {
    "name": "Special Guests",
    "released_at": "2023-11-17"
  },
  "alci": {
    "name": "The Lost Caverns of Ixalan Art Series",
    "released_at": "2023-11-17"
  },
  "plci": {
    "name": "The Lost Caverns of Ixalan Promos",
    "released_at": "2023-11-17"
  },
  "rex": {
    "name": "Jurassic World Collection",
    "released_at": "2023-11-17"
  },
  "lcc": {
    "name": "The Lost Caverns of Ixalan Commander",
    "released_at": "2023-11-17"
  },
  "pmat": {
    "name": "March of the Machine: The Aftermath Promos",
    "released_at": "2023-11-17"
  },
  "tlci": {
    "name": "The Lost Caverns of Ixalan Tokens",
    "released_at": "2023-11-17"
  },
  "lci": {
    "name": "The Lost Caverns of Ixalan",
    "released_at": "2023-11-17"
  },
  "slci": {
    "name": "The Lost Caverns of Ixalan Substitute Cards",
    "released_at": "2023-11-17"
  },
  "tlcc": {
    "name": "The Lost Caverns of Ixalan Commander Tokens",
    "released_at": "2023-11-17"
  },
  "trex": {
    "name": "Jurassic World Collection Tokens",
    "released_at": "2023-11-17"
  },
  "altc": {
    "name": "Tales of Middle-earth Scene Box",
    "released_at": "2023-11-04"
  },
  "who": {
    "name": "Doctor Who",
    "released_at": "2023-10-13"
  },
  "twho": {
    "name": "Doctor Who Tokens",
    "released_at": "2023-10-13"
  },
  "ywoe": {
    "name": "Alchemy: Wilds of Eldraine",
    "released_at": "2023-10-10"
  },
  "pwoe": {
    "name": "Wilds of Eldraine Promos",
    "released_at": "2023-09-08"
  },
  "wot": {
    "name": "Wilds of Eldraine: Enchanting Tales",
    "released_at": "2023-09-08"
  },
  "twoe": {
    "name": "Wilds of Eldraine Tokens",
    "released_at": "2023-09-08"
  },
  "twoc": {
    "name": "Wilds of Eldraine Commander Tokens",
    "released_at": "2023-09-08"
  },
  "woc": {
    "name": "Wilds of Eldraine Commander",
    "released_at": "2023-09-08"
  },
  "wwoe": {
    "name": "WOE Japanese Promo Tokens",
    "released_at": "2023-09-08"
  },
  "awoe": {
    "name": "Wilds of Eldraine Art Series",
    "released_at": "2023-09-08"
  },
  "pmda": {
    "name": "Magic × Duel Masters Promos",
    "released_at": "2023-09-08"
  },
  "ptsr": {
    "name": "Time Spiral Remastered Promos",
    "released_at": "2023-09-08"
  },
  "woe": {
    "name": "Wilds of Eldraine",
    "released_at": "2023-09-08"
  },
  "p30t": {
    "name": "30th Anniversary Celebration Tokyo",
    "released_at": "2023-09-01"
  },
  "acmm": {
    "name": "Commander Masters Art Series",
    "released_at": "2023-08-04"
  },
  "tcmm": {
    "name": "Commander Masters Tokens",
    "released_at": "2023-08-04"
  },
  "cmm": {
    "name": "Commander Masters",
    "released_at": "2023-08-04"
  },
  "ph22": {
    "name": "2022 Heroes of the Realm",
    "released_at": "2023-08-01"
  },
  "ea3": {
    "name": "Explorer Anthology 3",
    "released_at": "2023-07-18"
  },
  "ha7": {
    "name": "Historic Anthology 7",
    "released_at": "2023-07-18"
  },
  "pf23": {
    "name": "MagicFest 2023",
    "released_at": "2023-07-01"
  },
  "pltr": {
    "name": "Tales of Middle-earth Promos",
    "released_at": "2023-06-23"
  },
  "ltc": {
    "name": "Tales of Middle-earth Commander",
    "released_at": "2023-06-23"
  },
  "tltr": {
    "name": "Tales of Middle-earth Tokens",
    "released_at": "2023-06-23"
  },
  "tltc": {
    "name": "Tales of Middle-earth Commander Tokens",
    "released_at": "2023-06-23"
  },
  "altr": {
    "name": "Tales of Middle-earth Art Series",
    "released_at": "2023-06-23"
  },
  "mltr": {
    "name": "The Lord of the Rings: Tales of Middle-earth Minigames",
    "released_at": "2023-06-23"
  },
  "fltr": {
    "name": "Tales of Middle-earth Front Cards",
    "released_at": "2023-06-23"
  },
  "ltr": {
    "name": "The Lord of the Rings: Tales of Middle-earth",
    "released_at": "2023-06-23"
  },
  "mat": {
    "name": "March of the Machine: The Aftermath",
    "released_at": "2023-05-12"
  },
  "fmom": {
    "name": "March of the Machine Jumpstart Front Cards",
    "released_at": "2023-04-21"
  },
  "tmoc": {
    "name": "March of the Machine Commander Tokens",
    "released_at": "2023-04-21"
  },
  "pmom": {
    "name": "March of the Machine Promos",
    "released_at": "2023-04-21"
  },
  "moc": {
    "name": "March of the Machine Commander",
    "released_at": "2023-04-21"
  },
  "smom": {
    "name": "March of the Machine Substitute Cards",
    "released_at": "2023-04-21"
  },
  "mom": {
    "name": "March of the Machine",
    "released_at": "2023-04-21"
  },
  "tmul": {
    "name": "Multiverse Legends Tokens",
    "released_at": "2023-04-21"
  },
  "wmom": {
    "name": "MOM Japanese Promo Tokens",
    "released_at": "2023-04-21"
  },
  "amom": {
    "name": "March of the Machine Art Series",
    "released_at": "2023-04-21"
  },
  "tmom": {
    "name": "March of the Machine Tokens",
    "released_at": "2023-04-21"
  },
  "mul": {
    "name": "Multiverse Legends",
    "released_at": "2023-04-21"
  },
  "sis": {
    "name": "Shadows of the Past",
    "released_at": "2023-03-21"
  },
  "sir": {
    "name": "Shadows over Innistrad Remastered",
    "released_at": "2023-03-21"
  },
  "yone": {
    "name": "Alchemy: Phyrexia",
    "released_at": "2023-02-28"
  },
  "slp": {
    "name": "Secret Lair Promo",
    "released_at": "2023-02-17"
  },
  "unk": {
    "name": "Unknown Event",
    "released_at": "2023-02-15"
  },
  "pl23": {
    "name": "Year of the Rabbit 2023",
    "released_at": "2023-02-10"
  },
  "aone": {
    "name": "Phyrexia: All Will Be One Art Series",
    "released_at": "2023-02-10"
  },
  "mone": {
    "name": "Phyrexia: All Will Be One Minigames",
    "released_at": "2023-02-10"
  },
  "fone": {
    "name": "Phyrexia: All Will Be One Jumpstart Front Cards",
    "released_at": "2023-02-10"
  },
  "pone": {
    "name": "Phyrexia: All Will Be One Promos",
    "released_at": "2023-02-10"
  },
  "one": {
    "name": "Phyrexia: All Will Be One",
    "released_at": "2023-02-10"
  },
  "onc": {
    "name": "Phyrexia: All Will Be One Commander",
    "released_at": "2023-02-10"
  },
  "tonc": {
    "name": "Phyrexia: All Will Be One Commander Tokens",
    "released_at": "2023-02-03"
  },
  "tone": {
    "name": "Phyrexia: All Will Be One Tokens",
    "released_at": "2023-02-03"
  },
  "wone": {
    "name": "ONE Japanese Promo Tokens",
    "released_at": "2023-01-27"
  },
  "dmr": {
    "name": "Dominaria Remastered",
    "released_at": "2023-01-13"
  },
  "tdmr": {
    "name": "Dominaria Remastered Tokens",
    "released_at": "2023-01-13"
  },
  "pr23": {
    "name": "Regional Championship Qualifiers 2023",
    "released_at": "2023-01-07"
  },
  "p23": {
    "name": "Judge Gift Cards 2023",
    "released_at": "2023-01-01"
  },
  "pw23": {
    "name": "Wizards Play Network 2023",
    "released_at": "2023-01-01"
  },
  "ybro": {
    "name": "Alchemy: The Brothers' War",
    "released_at": "2022-12-13"
  },
  "ea2": {
    "name": "Explorer Anthology 2",
    "released_at": "2022-12-13"
  },
  "tscd": {
    "name": "Starter Commander Deck Tokens",
    "released_at": "2022-12-02"
  },
  "scd": {
    "name": "Starter Commander Decks",
    "released_at": "2022-12-02"
  },
  "fj22": {
    "name": "Jumpstart 2022 Front Cards",
    "released_at": "2022-12-02"
  },
  "j22": {
    "name": "Jumpstart 2022",
    "released_at": "2022-12-02"
  },
  "30a": {
    "name": "30th Anniversary Edition",
    "released_at": "2022-11-28"
  },
  "t30a": {
    "name": "30th Anniversary Tokens",
    "released_at": "2022-11-28"
  },
  "pewk": {
    "name": "Eternal Weekend",
    "released_at": "2022-11-26"
  },
  "brc": {
    "name": "The Brothers' War Commander",
    "released_at": "2022-11-18"
  },
  "brr": {
    "name": "The Brothers' War Retro Artifacts",
    "released_at": "2022-11-18"
  },
  "pbro": {
    "name": "The Brothers' War Promos",
    "released_at": "2022-11-18"
  },
  "tbot": {
    "name": "Transformers Tokens",
    "released_at": "2022-11-18"
  },
  "bot": {
    "name": "Transformers",
    "released_at": "2022-11-18"
  },
  "ptbro": {
    "name": "The Brothers' War Southeast Asia Tokens",
    "released_at": "2022-11-18"
  },
  "abro": {
    "name": "The Brothers' War Art Series",
    "released_at": "2022-11-18"
  },
  "tbro": {
    "name": "The Brothers' War Tokens",
    "released_at": "2022-11-18"
  },
  "mbro": {
    "name": "The Brothers' War Minigames",
    "released_at": "2022-11-18"
  },
  "bro": {
    "name": "The Brothers' War",
    "released_at": "2022-11-18"
  },
  "tbrc": {
    "name": "The Brothers' War Commander Tokens",
    "released_at": "2022-11-18"
  },
  "fbro": {
    "name": "The Brothers' War Jumpstart Front Cards",
    "released_at": "2022-11-18"
  },
  "sbro": {
    "name": "The Brothers' War Substitute Cards",
    "released_at": "2022-11-18"
  },
  "slc": {
    "name": "Secret Lair Countdown",
    "released_at": "2022-11-01"
  },
  "tgn3": {
    "name": "Game Night: Free-for-All Tokens",
    "released_at": "2022-10-14"
  },
  "gn3": {
    "name": "Game Night: Free-for-All",
    "released_at": "2022-10-14"
  },
  "ulst": {
    "name": "The List (Unfinity Foil Edition)",
    "released_at": "2022-10-07"
  },
  "unf": {
    "name": "Unfinity",
    "released_at": "2022-10-07"
  },
  "sunf": {
    "name": "Unfinity Sticker Sheets",
    "released_at": "2022-10-07"
  },
  "tunf": {
    "name": "Unfinity Tokens",
    "released_at": "2022-10-07"
  },
  "t40k": {
    "name": "Warhammer 40,000 Tokens",
    "released_at": "2022-10-07"
  },
  "40k": {
    "name": "Warhammer 40,000 Commander",
    "released_at": "2022-10-07"
  },
  "ydmu": {
    "name": "Alchemy: Dominaria",
    "released_at": "2022-10-05"
  },
  "prcq": {
    "name": "Regional Championship Qualifiers 2022",
    "released_at": "2022-10-01"
  },
  "p30h": {
    "name": "30th Anniversary History Promos",
    "released_at": "2022-09-09"
  },
  "pdmu": {
    "name": "Dominaria United Promos",
    "released_at": "2022-09-09"
  },
  "ptdmu": {
    "name": "Dominaria United Southeast Asia Tokens",
    "released_at": "2022-09-09"
  },
  "mdmu": {
    "name": "Dominaria United Minigames",
    "released_at": "2022-09-09"
  },
  "dmc": {
    "name": "Dominaria United Commander",
    "released_at": "2022-09-09"
  },
  "tdmc": {
    "name": "Dominaria United Commander Tokens",
    "released_at": "2022-09-09"
  },
  "wdmu": {
    "name": "DMU Japanese Promo Tokens",
    "released_at": "2022-09-09"
  },
  "dmu": {
    "name": "Dominaria United",
    "released_at": "2022-09-09"
  },
  "tdmu": {
    "name": "Dominaria United Tokens",
    "released_at": "2022-09-09"
  },
  "admu": {
    "name": "Dominaria United Art Series",
    "released_at": "2022-09-09"
  },
  "fdmu": {
    "name": "Dominaria United Jumpstart Front Cards",
    "released_at": "2022-09-09"
  },
  "p30a": {
    "name": "30th Anniversary Play Promos",
    "released_at": "2022-09-02"
  },
  "p30m": {
    "name": "30th Anniversary Misc Promos",
    "released_at": "2022-09-02"
  },
  "ph21": {
    "name": "2021 Heroes of the Realm",
    "released_at": "2022-08-01"
  },
  "psvc": {
    "name": "Summer Vacation Promos 2022",
    "released_at": "2022-08-01"
  },
  "ea1": {
    "name": "Explorer Anthology 1",
    "released_at": "2022-07-28"
  },
  "ha6": {
    "name": "Historic Anthology 6",
    "released_at": "2022-07-28"
  },
  "sch": {
    "name": "Store Championships",
    "released_at": "2022-07-09"
  },
  "t2x2": {
    "name": "Double Masters 2022 Tokens",
    "released_at": "2022-07-08"
  },
  "2x2": {
    "name": "Double Masters 2022",
    "released_at": "2022-07-08"
  },
  "hbg": {
    "name": "Alchemy Horizons: Baldur's Gate",
    "released_at": "2022-07-07"
  },
  "plg22": {
    "name": "Love Your LGS 2022",
    "released_at": "2022-07-01"
  },
  "pclb": {
    "name": "Battle for Baldur's Gate Promos",
    "released_at": "2022-06-10"
  },
  "mclb": {
    "name": "Commander Legends: Battle for Baldur's Gate Minigames",
    "released_at": "2022-06-10"
  },
  "aclb": {
    "name": "Battle for Baldur's Gate Art Series",
    "released_at": "2022-06-10"
  },
  "tclb": {
    "name": "Battle for Baldur's Gate Tokens",
    "released_at": "2022-06-10"
  },
  "oclb": {
    "name": "Battle for Baldur's Gate Oversized Cards",
    "released_at": "2022-06-10"
  },
  "clb": {
    "name": "Commander Legends: Battle for Baldur's Gate",
    "released_at": "2022-06-10"
  },
  "ysnc": {
    "name": "Alchemy: New Capenna",
    "released_at": "2022-06-02"
  },
  "ptsnc": {
    "name": "Streets of New Capenna Southeast Asia Tokens",
    "released_at": "2022-04-30"
  },
  "pncc": {
    "name": "New Capenna Commander Promos",
    "released_at": "2022-04-29"
  },
  "tsnc": {
    "name": "Streets of New Capenna Tokens",
    "released_at": "2022-04-29"
  },
  "snc": {
    "name": "Streets of New Capenna",
    "released_at": "2022-04-29"
  },
  "tncc": {
    "name": "New Capenna Commander Tokens",
    "released_at": "2022-04-29"
  },
  "ncc": {
    "name": "New Capenna Commander",
    "released_at": "2022-04-29"
  },
  "psnc": {
    "name": "Streets of New Capenna Promos",
    "released_at": "2022-04-29"
  },
  "msnc": {
    "name": "Streets of New Capenna Minigames",
    "released_at": "2022-04-29"
  },
  "asnc": {
    "name": "New Capenna Art Series",
    "released_at": "2022-04-29"
  },
  "gdy": {
    "name": "Game Day Promos",
    "released_at": "2022-04-08"
  },
  "q07": {
    "name": "Challenger Decks 2022",
    "released_at": "2022-04-01"
  },
  "yneo": {
    "name": "Alchemy: Kamigawa",
    "released_at": "2022-03-17"
  },
  "pw22": {
    "name": "Wizards Play Network 2022",
    "released_at": "2022-03-05"
  },
  "slx": {
    "name": "Universes Within",
    "released_at": "2022-03-03"
  },
  "pl22": {
    "name": "Year of the Tiger 2022",
    "released_at": "2022-02-25"
  },
  "pneo": {
    "name": "Kamigawa: Neon Dynasty Promos",
    "released_at": "2022-02-18"
  },
  "mneo": {
    "name": "Kamigawa: Neon Dynasty Minigames",
    "released_at": "2022-02-18"
  },
  "sneo": {
    "name": "Kamigawa: Neon Dynasty Substitute Cards",
    "released_at": "2022-02-18"
  },
  "tneo": {
    "name": "Kamigawa: Neon Dynasty Tokens",
    "released_at": "2022-02-18"
  },
  "tnec": {
    "name": "Neon Dynasty Commander Tokens",
    "released_at": "2022-02-18"
  },
  "neo": {
    "name": "Kamigawa: Neon Dynasty",
    "released_at": "2022-02-18"
  },
  "nec": {
    "name": "Neon Dynasty Commander",
    "released_at": "2022-02-18"
  },
  "aneo": {
    "name": "Neon Dynasty Art Series",
    "released_at": "2022-02-18"
  },
  "cc2": {
    "name": "Commander Collection: Black",
    "released_at": "2022-01-28"
  },
  "dbl": {
    "name": "Innistrad: Double Feature",
    "released_at": "2022-01-28"
  },
  "p22": {
    "name": "Judge Gift Cards 2022",
    "released_at": "2022-01-01"
  },
  "ymid": {
    "name": "Alchemy: Innistrad",
    "released_at": "2021-12-09"
  },
  "pvow": {
    "name": "Innistrad: Crimson Vow Promos",
    "released_at": "2021-11-19"
  },
  "tvoc": {
    "name": "Crimson Vow Commander Tokens",
    "released_at": "2021-11-19"
  },
  "tvow": {
    "name": "Innistrad: Crimson Vow Tokens",
    "released_at": "2021-11-19"
  },
  "ovoc": {
    "name": "Crimson Vow Commander Display Commanders",
    "released_at": "2021-11-19"
  },
  "mvow": {
    "name": "Innistrad: Crimson Vow Minigames",
    "released_at": "2021-11-19"
  },
  "svow": {
    "name": "Innistrad: Crimson Vow Substitute Cards",
    "released_at": "2021-11-19"
  },
  "avow": {
    "name": "Crimson Vow Art Series",
    "released_at": "2021-11-19"
  },
  "voc": {
    "name": "Crimson Vow Commander",
    "released_at": "2021-11-19"
  },
  "vow": {
    "name": "Innistrad: Crimson Vow",
    "released_at": "2021-11-19"
  },
  "q06": {
    "name": "Pioneer Challenger Decks 2021",
    "released_at": "2021-10-15"
  },
  "smid": {
    "name": "Innistrad: Midnight Hunt Substitute Cards",
    "released_at": "2021-09-24"
  },
  "omic": {
    "name": "Midnight Hunt Commander Display Commanders",
    "released_at": "2021-09-24"
  },
  "tmic": {
    "name": "Midnight Hunt Commander Tokens",
    "released_at": "2021-09-24"
  },
  "tmid": {
    "name": "Innistrad: Midnight Hunt Tokens",
    "released_at": "2021-09-24"
  },
  "mic": {
    "name": "Midnight Hunt Commander",
    "released_at": "2021-09-24"
  },
  "amid": {
    "name": "Midnight Hunt Art Series",
    "released_at": "2021-09-24"
  },
  "pmid": {
    "name": "Innistrad: Midnight Hunt Promos",
    "released_at": "2021-09-24"
  },
  "mid": {
    "name": "Innistrad: Midnight Hunt",
    "released_at": "2021-09-24"
  },
  "mmid": {
    "name": "Innistrad: Midnight Hunt Minigames",
    "released_at": "2021-09-24"
  },
  "j21": {
    "name": "Jumpstart: Historic Horizons",
    "released_at": "2021-08-26"
  },
  "cmb2": {
    "name": "Mystery Booster Playtest Cards 2021",
    "released_at": "2021-08-20"
  },
  "ph20": {
    "name": "2020 Heroes of the Realm",
    "released_at": "2021-08-01"
  },
  "pafr": {
    "name": "Adventures in the Forgotten Realms Promos",
    "released_at": "2021-07-23"
  },
  "oafr": {
    "name": "Forgotten Realms Oversized Cards",
    "released_at": "2021-07-23"
  },
  "oafc": {
    "name": "Forgotten Realms Commander Display Commanders",
    "released_at": "2021-07-23"
  },
  "aafr": {
    "name": "Adventures in the Forgotten Realms Art Series",
    "released_at": "2021-07-23"
  },
  "afc": {
    "name": "Forgotten Realms Commander",
    "released_at": "2021-07-23"
  },
  "tafc": {
    "name": "Forgotten Realms Commander Tokens",
    "released_at": "2021-07-23"
  },
  "tafr": {
    "name": "Adventures in the Forgotten Realms Tokens",
    "released_at": "2021-07-23"
  },
  "mafr": {
    "name": "Adventures in the Forgotten Realms Minigames",
    "released_at": "2021-07-23"
  },
  "afr": {
    "name": "Adventures in the Forgotten Realms",
    "released_at": "2021-07-23"
  },
  "plg21": {
    "name": "Love Your LGS 2021",
    "released_at": "2021-06-22"
  },
  "tmh2": {
    "name": "Modern Horizons 2 Tokens",
    "released_at": "2021-06-18"
  },
  "amh2": {
    "name": "Modern Horizons 2 Art Series",
    "released_at": "2021-06-18"
  },
  "mmh2": {
    "name": "Modern Horizons 2 Minigames",
    "released_at": "2021-06-18"
  },
  "pmh2": {
    "name": "Modern Horizons 2 Promos",
    "released_at": "2021-06-18"
  },
  "pw21": {
    "name": "Wizards Play Network 2021",
    "released_at": "2021-06-18"
  },
  "h1r": {
    "name": "Modern Horizons 1 Timeshifts",
    "released_at": "2021-06-18"
  },
  "mh2": {
    "name": "Modern Horizons 2",
    "released_at": "2021-06-18"
  },
  "ha5": {
    "name": "Historic Anthology 5",
    "released_at": "2021-05-27"
  },
  "pstx": {
    "name": "Strixhaven: School of Mages Promos",
    "released_at": "2021-04-23"
  },
  "tc21": {
    "name": "Commander 2021 Tokens",
    "released_at": "2021-04-23"
  },
  "tstx": {
    "name": "Strixhaven: School of Mages Tokens",
    "released_at": "2021-04-23"
  },
  "sstx": {
    "name": "Strixhaven: School of Mages Substitute Cards",
    "released_at": "2021-04-23"
  },
  "mstx": {
    "name": "Strixhaven: School of Mages Minigames",
    "released_at": "2021-04-23"
  },
  "stx": {
    "name": "Strixhaven: School of Mages",
    "released_at": "2021-04-23"
  },
  "oc21": {
    "name": "Commander 2021 Display Commanders",
    "released_at": "2021-04-23"
  },
  "c21": {
    "name": "Commander 2021",
    "released_at": "2021-04-23"
  },
  "sta": {
    "name": "Strixhaven Mystical Archive",
    "released_at": "2021-04-23"
  },
  "astx": {
    "name": "Strixhaven Art Series",
    "released_at": "2021-04-23"
  },
  "tsr": {
    "name": "Time Spiral Remastered",
    "released_at": "2021-03-19"
  },
  "ttsr": {
    "name": "Time Spiral Remastered Tokens",
    "released_at": "2021-03-19"
  },
  "ha4": {
    "name": "Historic Anthology 4",
    "released_at": "2021-03-11"
  },
  "pkhm": {
    "name": "Kaldheim Promos",
    "released_at": "2021-02-05"
  },
  "mkhm": {
    "name": "Kaldheim Minigames",
    "released_at": "2021-02-05"
  },
  "skhm": {
    "name": "Kaldheim Substitute Cards",
    "released_at": "2021-02-05"
  },
  "akhm": {
    "name": "Kaldheim Art Series",
    "released_at": "2021-02-05"
  },
  "tkhc": {
    "name": "Kaldheim Commander Tokens",
    "released_at": "2021-02-05"
  },
  "tkhm": {
    "name": "Kaldheim Tokens",
    "released_at": "2021-02-05"
  },
  "khm": {
    "name": "Kaldheim",
    "released_at": "2021-02-05"
  },
  "khc": {
    "name": "Kaldheim Commander",
    "released_at": "2021-02-05"
  },
  "pl21": {
    "name": "Year of the Ox 2021",
    "released_at": "2021-01-25"
  },
  "pj21": {
    "name": "Judge Gift Cards 2021",
    "released_at": "2021-01-01"
  },
  "cc1": {
    "name": "Commander Collection: Green",
    "released_at": "2020-12-04"
  },
  "tcmr": {
    "name": "Commander Legends Tokens",
    "released_at": "2020-11-20"
  },
  "cmr": {
    "name": "Commander Legends",
    "released_at": "2020-11-20"
  },
  "pcmr": {
    "name": "Commander Legends Promos",
    "released_at": "2020-11-20"
  },
  "klr": {
    "name": "Kaladesh Remastered",
    "released_at": "2020-11-12"
  },
  "plst": {
    "name": "The List",
    "released_at": "2020-09-26"
  },
  "pznr": {
    "name": "Zendikar Rising Promos",
    "released_at": "2020-09-25"
  },
  "tznc": {
    "name": "Zendikar Rising Commander Tokens",
    "released_at": "2020-09-25"
  },
  "zne": {
    "name": "Zendikar Rising Expeditions",
    "released_at": "2020-09-25"
  },
  "znr": {
    "name": "Zendikar Rising",
    "released_at": "2020-09-25"
  },
  "aznr": {
    "name": "Zendikar Rising Art Series",
    "released_at": "2020-09-25"
  },
  "znc": {
    "name": "Zendikar Rising Commander",
    "released_at": "2020-09-25"
  },
  "mznr": {
    "name": "Zendikar Rising Minigames",
    "released_at": "2020-09-25"
  },
  "tznr": {
    "name": "Zendikar Rising Tokens",
    "released_at": "2020-09-25"
  },
  "sznr": {
    "name": "Zendikar Rising Substitute Cards",
    "released_at": "2020-09-25"
  },
  "anb": {
    "name": "Arena Beginner Set",
    "released_at": "2020-08-13"
  },
  "akr": {
    "name": "Amonkhet Remastered",
    "released_at": "2020-08-13"
  },
  "2xm": {
    "name": "Double Masters",
    "released_at": "2020-08-07"
  },
  "t2xm": {
    "name": "Double Masters Tokens",
    "released_at": "2020-08-07"
  },
  "ph19": {
    "name": "2019 Heroes of the Realm",
    "released_at": "2020-08-01"
  },
  "ajmp": {
    "name": "Jumpstart Arena Exclusives",
    "released_at": "2020-07-17"
  },
  "jmp": {
    "name": "Jumpstart",
    "released_at": "2020-07-17"
  },
  "pm21": {
    "name": "Core Set 2021 Promos",
    "released_at": "2020-07-03"
  },
  "tm21": {
    "name": "Core Set 2021 Tokens",
    "released_at": "2020-07-03"
  },
  "m21": {
    "name": "Core Set 2021",
    "released_at": "2020-07-03"
  },
  "ss3": {
    "name": "Signature Spellbook: Chandra",
    "released_at": "2020-06-26"
  },
  "fjmp": {
    "name": "Jumpstart Front Cards",
    "released_at": "2020-06-18"
  },
  "slu": {
    "name": "Secret Lair: Ultimate Edition",
    "released_at": "2020-05-29"
  },
  "ha3": {
    "name": "Historic Anthology 3",
    "released_at": "2020-05-21"
  },
  "plg20": {
    "name": "Love Your LGS 2020",
    "released_at": "2020-05-18"
  },
  "piko": {
    "name": "Ikoria: Lair of Behemoths Promos",
    "released_at": "2020-04-24"
  },
  "tiko": {
    "name": "Ikoria: Lair of Behemoths Tokens",
    "released_at": "2020-04-24"
  },
  "iko": {
    "name": "Ikoria: Lair of Behemoths",
    "released_at": "2020-04-24"
  },
  "oc20": {
    "name": "Commander 2020 Oversized",
    "released_at": "2020-04-17"
  },
  "tc20": {
    "name": "Commander 2020 Tokens",
    "released_at": "2020-04-17"
  },
  "c20": {
    "name": "Commander 2020",
    "released_at": "2020-04-17"
  },
  "ha2": {
    "name": "Historic Anthology 2",
    "released_at": "2020-03-12"
  },
  "tund": {
    "name": "Unsanctioned Tokens",
    "released_at": "2020-02-29"
  },
  "und": {
    "name": "Unsanctioned",
    "released_at": "2020-02-29"
  },
  "pthb": {
    "name": "Theros Beyond Death Promos",
    "released_at": "2020-01-24"
  },
  "tthb": {
    "name": "Theros Beyond Death Tokens",
    "released_at": "2020-01-24"
  },
  "thb": {
    "name": "Theros Beyond Death",
    "released_at": "2020-01-24"
  },
  "j20": {
    "name": "Judge Gift Cards 2020",
    "released_at": "2020-01-01"
  },
  "pf20": {
    "name": "MagicFest 2020",
    "released_at": "2020-01-01"
  },
  "sld": {
    "name": "Secret Lair Drop",
    "released_at": "2019-12-02"
  },
  "ha1": {
    "name": "Historic Anthology 1",
    "released_at": "2019-11-21"
  },
  "tgn2": {
    "name": "Game Night 2019 Tokens",
    "released_at": "2019-11-15"
  },
  "gn2": {
    "name": "Game Night 2019",
    "released_at": "2019-11-15"
  },
  "cmb1": {
    "name": "Mystery Booster Playtest Cards 2019",
    "released_at": "2019-11-07"
  },
  "ptg": {
    "name": "Ponies: The Galloping",
    "released_at": "2019-10-22"
  },
  "peld": {
    "name": "Throne of Eldraine Promos",
    "released_at": "2019-10-04"
  },
  "teld": {
    "name": "Throne of Eldraine Tokens",
    "released_at": "2019-10-04"
  },
  "eld": {
    "name": "Throne of Eldraine",
    "released_at": "2019-10-04"
  },
  "pwcs": {
    "name": "Planeswalker Championship Promos",
    "released_at": "2019-10-01"
  },
  "c19": {
    "name": "Commander 2019",
    "released_at": "2019-08-23"
  },
  "oc19": {
    "name": "Commander 2019 Oversized",
    "released_at": "2019-08-23"
  },
  "tc19": {
    "name": "Commander 2019 Tokens",
    "released_at": "2019-08-01"
  },
  "ph18": {
    "name": "2018 Heroes of the Realm",
    "released_at": "2019-08-01"
  },
  "ps19": {
    "name": "San Diego Comic-Con 2019",
    "released_at": "2019-07-18"
  },
  "ppp1": {
    "name": "M20 Promo Packs",
    "released_at": "2019-07-12"
  },
  "tm20": {
    "name": "Core Set 2020 Tokens",
    "released_at": "2019-07-12"
  },
  "pm20": {
    "name": "Core Set 2020 Promos",
    "released_at": "2019-07-12"
  },
  "m20": {
    "name": "Core Set 2020",
    "released_at": "2019-07-12"
  },
  "ss2": {
    "name": "Signature Spellbook: Gideon",
    "released_at": "2019-06-28"
  },
  "pmh1": {
    "name": "Modern Horizons Promos",
    "released_at": "2019-06-14"
  },
  "mh1": {
    "name": "Modern Horizons",
    "released_at": "2019-06-14"
  },
  "amh1": {
    "name": "Modern Horizons Art Series",
    "released_at": "2019-06-14"
  },
  "tmh1": {
    "name": "Modern Horizons Tokens",
    "released_at": "2019-05-30"
  },
  "pwar": {
    "name": "War of the Spark Promos",
    "released_at": "2019-05-03"
  },
  "twar": {
    "name": "War of the Spark Tokens",
    "released_at": "2019-05-03"
  },
  "war": {
    "name": "War of the Spark",
    "released_at": "2019-05-03"
  },
  "j19": {
    "name": "Judge Gift Cards 2019",
    "released_at": "2019-04-10"
  },
  "prw2": {
    "name": "RNA Ravnica Weekend",
    "released_at": "2019-02-16"
  },
  "tgk2": {
    "name": "RNA Guild Kit Tokens",
    "released_at": "2019-02-15"
  },
  "gk2": {
    "name": "RNA Guild Kit",
    "released_at": "2019-02-15"
  },
  "prna": {
    "name": "Ravnica Allegiance Promos",
    "released_at": "2019-01-25"
  },
  "trna": {
    "name": "Ravnica Allegiance Tokens",
    "released_at": "2019-01-25"
  },
  "rna": {
    "name": "Ravnica Allegiance",
    "released_at": "2019-01-25"
  },
  "pf19": {
    "name": "MagicFest 2019",
    "released_at": "2019-01-01"
  },
  "puma": {
    "name": "Ultimate Box Topper",
    "released_at": "2018-12-07"
  },
  "tuma": {
    "name": "Ultimate Masters Tokens",
    "released_at": "2018-12-07"
  },
  "uma": {
    "name": "Ultimate Masters",
    "released_at": "2018-12-07"
  },
  "g18": {
    "name": "M19 Gift Pack",
    "released_at": "2018-11-16"
  },
  "gnt": {
    "name": "Game Night",
    "released_at": "2018-11-16"
  },
  "prwk": {
    "name": "GRN Ravnica Weekend",
    "released_at": "2018-11-09"
  },
  "tgk1": {
    "name": "GRN Guild Kit Tokens",
    "released_at": "2018-11-02"
  },
  "gk1": {
    "name": "GRN Guild Kit",
    "released_at": "2018-11-02"
  },
  "pgrn": {
    "name": "Guilds of Ravnica Promos",
    "released_at": "2018-10-05"
  },
  "tgrn": {
    "name": "Guilds of Ravnica Tokens",
    "released_at": "2018-10-05"
  },
  "grn": {
    "name": "Guilds of Ravnica",
    "released_at": "2018-10-05"
  },
  "med": {
    "name": "Mythic Edition",
    "released_at": "2018-10-05"
  },
  "tmed": {
    "name": "Mythic Edition Tokens",
    "released_at": "2018-10-05"
  },
  "oc18": {
    "name": "Commander 2018 Oversized",
    "released_at": "2018-08-10"
  },
  "c18": {
    "name": "Commander 2018",
    "released_at": "2018-08-10"
  },
  "tc18": {
    "name": "Commander 2018 Tokens",
    "released_at": "2018-08-09"
  },
  "ph17": {
    "name": "2017 Heroes of the Realm",
    "released_at": "2018-08-01"
  },
  "ps18": {
    "name": "San Diego Comic-Con 2018",
    "released_at": "2018-07-19"
  },
  "xana": {
    "name": "Arena New Player Experience Extras",
    "released_at": "2018-07-14"
  },
  "ana": {
    "name": "Arena New Player Experience",
    "released_at": "2018-07-14"
  },
  "pana": {
    "name": "MTG Arena Promos",
    "released_at": "2018-07-14"
  },
  "oana": {
    "name": "Arena New Player Experience Cards",
    "released_at": "2018-07-14"
  },
  "pm19": {
    "name": "Core Set 2019 Promos",
    "released_at": "2018-07-13"
  },
  "m19": {
    "name": "Core Set 2019",
    "released_at": "2018-07-13"
  },
  "pss3": {
    "name": "M19 Standard Showdown",
    "released_at": "2018-07-13"
  },
  "tm19": {
    "name": "Core Set 2019 Tokens",
    "released_at": "2018-07-13"
  },
  "gs1": {
    "name": "Global Series Jiang Yanggu & Mu Yanling",
    "released_at": "2018-06-22"
  },
  "ss1": {
    "name": "Signature Spellbook: Jace",
    "released_at": "2018-06-15"
  },
  "pbbd": {
    "name": "Battlebond Promos",
    "released_at": "2018-06-08"
  },
  "tbbd": {
    "name": "Battlebond Tokens",
    "released_at": "2018-06-08"
  },
  "tcm2": {
    "name": "Commander Anthology Volume II Tokens",
    "released_at": "2018-06-08"
  },
  "bbd": {
    "name": "Battlebond",
    "released_at": "2018-06-08"
  },
  "cm2": {
    "name": "Commander Anthology Volume II",
    "released_at": "2018-06-08"
  },
  "pdom": {
    "name": "Dominaria Promos",
    "released_at": "2018-04-27"
  },
  "tdom": {
    "name": "Dominaria Tokens",
    "released_at": "2018-04-27"
  },
  "dom": {
    "name": "Dominaria",
    "released_at": "2018-04-27"
  },
  "tddu": {
    "name": "Duel Decks: Elves vs. Inventors Tokens",
    "released_at": "2018-04-06"
  },
  "ddu": {
    "name": "Duel Decks: Elves vs. Inventors",
    "released_at": "2018-04-06"
  },
  "a25": {
    "name": "Masters 25",
    "released_at": "2018-03-16"
  },
  "ta25": {
    "name": "Masters 25 Tokens",
    "released_at": "2018-03-16"
  },
  "plny": {
    "name": "Lunar New Year 2018",
    "released_at": "2018-02-16"
  },
  "pnat": {
    "name": "Nationals Promos",
    "released_at": "2018-01-25"
  },
  "trix": {
    "name": "Rivals of Ixalan Tokens",
    "released_at": "2018-01-19"
  },
  "prix": {
    "name": "Rivals of Ixalan Promos",
    "released_at": "2018-01-19"
  },
  "rix": {
    "name": "Rivals of Ixalan",
    "released_at": "2018-01-19"
  },
  "j18": {
    "name": "Judge Gift Cards 2018",
    "released_at": "2018-01-01"
  },
  "f18": {
    "name": "Friday Night Magic 2018",
    "released_at": "2017-12-27"
  },
  "pust": {
    "name": "Unstable Promos",
    "released_at": "2017-12-08"
  },
  "tust": {
    "name": "Unstable Tokens",
    "released_at": "2017-12-08"
  },
  "ust": {
    "name": "Unstable",
    "released_at": "2017-12-08"
  },
  "tima": {
    "name": "Iconic Masters Tokens",
    "released_at": "2017-11-29"
  },
  "e02": {
    "name": "Explorers of Ixalan",
    "released_at": "2017-11-24"
  },
  "pxtc": {
    "name": "XLN Treasure Chest",
    "released_at": "2017-11-24"
  },
  "v17": {
    "name": "From the Vault: Transform",
    "released_at": "2017-11-24"
  },
  "ima": {
    "name": "Iconic Masters",
    "released_at": "2017-11-17"
  },
  "ddt": {
    "name": "Duel Decks: Merfolk vs. Goblins",
    "released_at": "2017-10-24"
  },
  "tddt": {
    "name": "Duel Decks: Merfolk vs. Goblins Tokens",
    "released_at": "2017-10-24"
  },
  "g17": {
    "name": "2017 Gift Pack",
    "released_at": "2017-10-20"
  },
  "pxln": {
    "name": "Ixalan Promos",
    "released_at": "2017-09-29"
  },
  "xln": {
    "name": "Ixalan",
    "released_at": "2017-09-29"
  },
  "txln": {
    "name": "Ixalan Tokens",
    "released_at": "2017-09-29"
  },
  "pss2": {
    "name": "XLN Standard Showdown",
    "released_at": "2017-09-29"
  },
  "h17": {
    "name": "HasCon 2017",
    "released_at": "2017-09-20"
  },
  "phtr": {
    "name": "2016 Heroes of the Realm",
    "released_at": "2017-09-20"
  },
  "te01": {
    "name": "Archenemy: Nicol Bolas Tokens",
    "released_at": "2017-09-08"
  },
  "oc17": {
    "name": "Commander 2017 Oversized",
    "released_at": "2017-08-25"
  },
  "c17": {
    "name": "Commander 2017",
    "released_at": "2017-08-25"
  },
  "tc17": {
    "name": "Commander 2017 Tokens",
    "released_at": "2017-08-25"
  },
  "ps17": {
    "name": "San Diego Comic-Con 2017",
    "released_at": "2017-07-20"
  },
  "phou": {
    "name": "Hour of Devastation Promos",
    "released_at": "2017-07-14"
  },
  "hou": {
    "name": "Hour of Devastation",
    "released_at": "2017-07-14"
  },
  "thou": {
    "name": "Hour of Devastation Tokens",
    "released_at": "2017-07-14"
  },
  "oe01": {
    "name": "Archenemy: Nicol Bolas Schemes",
    "released_at": "2017-06-16"
  },
  "e01": {
    "name": "Archenemy: Nicol Bolas",
    "released_at": "2017-06-16"
  },
  "tcma": {
    "name": "Commander Anthology Tokens",
    "released_at": "2017-06-09"
  },
  "cma": {
    "name": "Commander Anthology",
    "released_at": "2017-06-09"
  },
  "pakh": {
    "name": "Amonkhet Promos",
    "released_at": "2017-04-28"
  },
  "takh": {
    "name": "Amonkhet Tokens",
    "released_at": "2017-04-28"
  },
  "mp2": {
    "name": "Amonkhet Invocations",
    "released_at": "2017-04-28"
  },
  "akh": {
    "name": "Amonkhet",
    "released_at": "2017-04-28"
  },
  "w17": {
    "name": "Welcome Deck 2017",
    "released_at": "2017-04-15"
  },
  "dds": {
    "name": "Duel Decks: Mind vs. Might",
    "released_at": "2017-03-31"
  },
  "tdds": {
    "name": "Duel Decks: Mind vs. Might Tokens",
    "released_at": "2017-03-31"
  },
  "mm3": {
    "name": "Modern Masters 2017",
    "released_at": "2017-03-17"
  },
  "tmm3": {
    "name": "Modern Masters 2017 Tokens",
    "released_at": "2017-03-17"
  },
  "paer": {
    "name": "Aether Revolt Promos",
    "released_at": "2017-01-20"
  },
  "taer": {
    "name": "Aether Revolt Tokens",
    "released_at": "2017-01-20"
  },
  "aer": {
    "name": "Aether Revolt",
    "released_at": "2017-01-20"
  },
  "l17": {
    "name": "League Tokens 2017",
    "released_at": "2017-01-01"
  },
  "f17": {
    "name": "Friday Night Magic 2017",
    "released_at": "2017-01-01"
  },
  "j17": {
    "name": "Judge Gift Cards 2017",
    "released_at": "2017-01-01"
  },
  "tpca": {
    "name": "Planechase Anthology Tokens",
    "released_at": "2016-11-25"
  },
  "pca": {
    "name": "Planechase Anthology",
    "released_at": "2016-11-25"
  },
  "opca": {
    "name": "Planechase Anthology Planes",
    "released_at": "2016-11-25"
  },
  "pz2": {
    "name": "Treasure Chest",
    "released_at": "2016-11-16"
  },
  "oc16": {
    "name": "Commander 2016 Oversized",
    "released_at": "2016-11-11"
  },
  "tc16": {
    "name": "Commander 2016 Tokens",
    "released_at": "2016-11-11"
  },
  "c16": {
    "name": "Commander 2016",
    "released_at": "2016-11-11"
  },
  "ps16": {
    "name": "San Diego Comic-Con 2016",
    "released_at": "2016-10-01"
  },
  "pkld": {
    "name": "Kaladesh Promos",
    "released_at": "2016-09-30"
  },
  "kld": {
    "name": "Kaladesh",
    "released_at": "2016-09-30"
  },
  "tkld": {
    "name": "Kaladesh Tokens",
    "released_at": "2016-09-30"
  },
  "mps": {
    "name": "Kaladesh Inventions",
    "released_at": "2016-09-30"
  },
  "ddr": {
    "name": "Duel Decks: Nissa vs. Ob Nixilis",
    "released_at": "2016-09-02"
  },
  "cn2": {
    "name": "Conspiracy: Take the Crown",
    "released_at": "2016-08-26"
  },
  "tcn2": {
    "name": "Conspiracy: Take the Crown Tokens",
    "released_at": "2016-08-26"
  },
  "v16": {
    "name": "From the Vault: Lore",
    "released_at": "2016-08-19"
  },
  "pemn": {
    "name": "Eldritch Moon Promos",
    "released_at": "2016-07-22"
  },
  "temn": {
    "name": "Eldritch Moon Tokens",
    "released_at": "2016-07-22"
  },
  "emn": {
    "name": "Eldritch Moon",
    "released_at": "2016-07-22"
  },
  "ema": {
    "name": "Eternal Masters",
    "released_at": "2016-06-10"
  },
  "tema": {
    "name": "Eternal Masters Tokens",
    "released_at": "2016-06-10"
  },
  "psoi": {
    "name": "Shadows over Innistrad Promos",
    "released_at": "2016-04-08"
  },
  "tsoi": {
    "name": "Shadows over Innistrad Tokens",
    "released_at": "2016-04-08"
  },
  "soi": {
    "name": "Shadows over Innistrad",
    "released_at": "2016-04-08"
  },
  "w16": {
    "name": "Welcome Deck 2016",
    "released_at": "2016-04-08"
  },
  "ddq": {
    "name": "Duel Decks: Blessed vs. Cursed",
    "released_at": "2016-02-26"
  },
  "togw": {
    "name": "Oath of the Gatewatch Tokens",
    "released_at": "2016-01-22"
  },
  "pogw": {
    "name": "Oath of the Gatewatch Promos",
    "released_at": "2016-01-22"
  },
  "ogw": {
    "name": "Oath of the Gatewatch",
    "released_at": "2016-01-22"
  },
  "l16": {
    "name": "League Tokens 2016",
    "released_at": "2016-01-01"
  },
  "j16": {
    "name": "Judge Gift Cards 2016",
    "released_at": "2016-01-01"
  },
  "f16": {
    "name": "Friday Night Magic 2016",
    "released_at": "2016-01-01"
  },
  "pz1": {
    "name": "Legendary Cube Prize Pack",
    "released_at": "2015-11-18"
  },
  "oc15": {
    "name": "Commander 2015 Oversized",
    "released_at": "2015-11-13"
  },
  "tc15": {
    "name": "Commander 2015 Tokens",
    "released_at": "2015-11-13"
  },
  "c15": {
    "name": "Commander 2015",
    "released_at": "2015-11-13"
  },
  "pbfz": {
    "name": "Battle for Zendikar Promos",
    "released_at": "2015-10-02"
  },
  "tbfz": {
    "name": "Battle for Zendikar Tokens",
    "released_at": "2015-10-02"
  },
  "pss1": {
    "name": "BFZ Standard Series",
    "released_at": "2015-10-02"
  },
  "exp": {
    "name": "Zendikar Expeditions",
    "released_at": "2015-10-02"
  },
  "bfz": {
    "name": "Battle for Zendikar",
    "released_at": "2015-10-02"
  },
  "ddp": {
    "name": "Duel Decks: Zendikar vs. Eldrazi",
    "released_at": "2015-08-28"
  },
  "v15": {
    "name": "From the Vault: Angels",
    "released_at": "2015-08-21"
  },
  "cp3": {
    "name": "Magic Origins Clash Pack",
    "released_at": "2015-07-17"
  },
  "pori": {
    "name": "Magic Origins Promos",
    "released_at": "2015-07-17"
  },
  "tori": {
    "name": "Magic Origins Tokens",
    "released_at": "2015-07-17"
  },
  "ori": {
    "name": "Magic Origins",
    "released_at": "2015-07-17"
  },
  "ps15": {
    "name": "San Diego Comic-Con 2015",
    "released_at": "2015-07-09"
  },
  "tmm2": {
    "name": "Modern Masters 2015 Tokens",
    "released_at": "2015-05-22"
  },
  "mm2": {
    "name": "Modern Masters 2015",
    "released_at": "2015-05-22"
  },
  "tpr": {
    "name": "Tempest Remastered",
    "released_at": "2015-05-06"
  },
  "ptkdf": {
    "name": "Tarkir Dragonfury",
    "released_at": "2015-04-03"
  },
  "pdtk": {
    "name": "Dragons of Tarkir Promos",
    "released_at": "2015-03-27"
  },
  "tdtk": {
    "name": "Dragons of Tarkir Tokens",
    "released_at": "2015-03-27"
  },
  "dtk": {
    "name": "Dragons of Tarkir",
    "released_at": "2015-03-27"
  },
  "ddo": {
    "name": "Duel Decks: Elspeth vs. Kiora",
    "released_at": "2015-02-27"
  },
  "pfrf": {
    "name": "Fate Reforged Promos",
    "released_at": "2015-01-23"
  },
  "cp2": {
    "name": "Fate Reforged Clash Pack",
    "released_at": "2015-01-23"
  },
  "frf": {
    "name": "Fate Reforged",
    "released_at": "2015-01-23"
  },
  "tfrf": {
    "name": "Fate Reforged Tokens",
    "released_at": "2015-01-23"
  },
  "ugin": {
    "name": "Ugin's Fate",
    "released_at": "2015-01-17"
  },
  "l15": {
    "name": "League Tokens 2015",
    "released_at": "2015-01-01"
  },
  "j15": {
    "name": "Judge Gift Cards 2015",
    "released_at": "2015-01-01"
  },
  "f15": {
    "name": "Friday Night Magic 2015",
    "released_at": "2015-01-01"
  },
  "tjvc": {
    "name": "Duel Decks Anthology: Jace vs. Chandra Tokens",
    "released_at": "2014-12-05"
  },
  "tdvd": {
    "name": "Duel Decks Anthology: Divine vs. Demonic Tokens",
    "released_at": "2014-12-05"
  },
  "tgvl": {
    "name": "Duel Decks Anthology: Garruk vs. Liliana Tokens",
    "released_at": "2014-12-05"
  },
  "tevg": {
    "name": "Duel Decks Anthology: Elves vs. Goblins Tokens",
    "released_at": "2014-12-05"
  },
  "jvc": {
    "name": "Duel Decks Anthology: Jace vs. Chandra",
    "released_at": "2014-12-05"
  },
  "gvl": {
    "name": "Duel Decks Anthology: Garruk vs. Liliana",
    "released_at": "2014-12-05"
  },
  "dvd": {
    "name": "Duel Decks Anthology: Divine vs. Demonic",
    "released_at": "2014-12-05"
  },
  "evg": {
    "name": "Duel Decks Anthology: Elves vs. Goblins",
    "released_at": "2014-12-05"
  },
  "oc14": {
    "name": "Commander 2014 Oversized",
    "released_at": "2014-11-07"
  },
  "tc14": {
    "name": "Commander 2014 Tokens",
    "released_at": "2014-11-07"
  },
  "c14": {
    "name": "Commander 2014",
    "released_at": "2014-11-07"
  },
  "pktk": {
    "name": "Khans of Tarkir Promos",
    "released_at": "2014-09-26"
  },
  "ktk": {
    "name": "Khans of Tarkir",
    "released_at": "2014-09-26"
  },
  "tktk": {
    "name": "Khans of Tarkir Tokens",
    "released_at": "2014-09-26"
  },
  "ddn": {
    "name": "Duel Decks: Speed vs. Cunning",
    "released_at": "2014-09-05"
  },
  "v14": {
    "name": "From the Vault: Annihilation",
    "released_at": "2014-08-22"
  },
  "cp1": {
    "name": "Magic 2015 Clash Pack",
    "released_at": "2014-07-18"
  },
  "m15": {
    "name": "Magic 2015",
    "released_at": "2014-07-18"
  },
  "tm15": {
    "name": "Magic 2015 Tokens",
    "released_at": "2014-07-18"
  },
  "pm15": {
    "name": "Magic 2015 Promos",
    "released_at": "2014-07-17"
  },
  "ppc1": {
    "name": "M15 Prerelease Challenge",
    "released_at": "2014-07-12"
  },
  "pdp15": {
    "name": "Duels of the Planeswalkers 2015 Promos",
    "released_at": "2014-07-09"
  },
  "ps14": {
    "name": "San Diego Comic-Con 2014",
    "released_at": "2014-07-08"
  },
  "vma": {
    "name": "Vintage Masters",
    "released_at": "2014-06-16"
  },
  "pcns": {
    "name": "Conspiracy Promos",
    "released_at": "2014-06-06"
  },
  "tcns": {
    "name": "Conspiracy Tokens",
    "released_at": "2014-06-06"
  },
  "cns": {
    "name": "Conspiracy",
    "released_at": "2014-06-06"
  },
  "md1": {
    "name": "Modern Event Deck 2014",
    "released_at": "2014-05-30"
  },
  "tmd1": {
    "name": "Modern Event Deck 2014 Tokens",
    "released_at": "2014-05-30"
  },
  "tdag": {
    "name": "Defeat a God",
    "released_at": "2014-05-25"
  },
  "jou": {
    "name": "Journey into Nyx",
    "released_at": "2014-05-02"
  },
  "thp3": {
    "name": "Journey into Nyx Hero's Path",
    "released_at": "2014-05-02"
  },
  "tjou": {
    "name": "Journey into Nyx Tokens",
    "released_at": "2014-05-02"
  },
  "pjou": {
    "name": "Journey into Nyx Promos",
    "released_at": "2014-04-26"
  },
  "ddm": {
    "name": "Duel Decks: Jace vs. Vraska",
    "released_at": "2014-03-14"
  },
  "tddm": {
    "name": "Duel Decks: Jace vs. Vraska Tokens",
    "released_at": "2014-03-14"
  },
  "tbth": {
    "name": "Battle the Horde",
    "released_at": "2014-03-01"
  },
  "tbng": {
    "name": "Born of the Gods Tokens",
    "released_at": "2014-02-07"
  },
  "thp2": {
    "name": "Born of the Gods Hero's Path",
    "released_at": "2014-02-07"
  },
  "bng": {
    "name": "Born of the Gods",
    "released_at": "2014-02-07"
  },
  "pbng": {
    "name": "Born of the Gods Promos",
    "released_at": "2014-02-01"
  },
  "l14": {
    "name": "League Tokens 2014",
    "released_at": "2014-01-01"
  },
  "f14": {
    "name": "Friday Night Magic 2014",
    "released_at": "2014-01-01"
  },
  "j14": {
    "name": "Judge Gift Cards 2014",
    "released_at": "2014-01-01"
  },
  "oc13": {
    "name": "Commander 2013 Oversized",
    "released_at": "2013-11-01"
  },
  "c13": {
    "name": "Commander 2013",
    "released_at": "2013-11-01"
  },
  "tfth": {
    "name": "Face the Hydra",
    "released_at": "2013-10-19"
  },
  "tths": {
    "name": "Theros Tokens",
    "released_at": "2013-09-27"
  },
  "ths": {
    "name": "Theros",
    "released_at": "2013-09-27"
  },
  "thp1": {
    "name": "Theros Hero's Path",
    "released_at": "2013-09-27"
  },
  "pths": {
    "name": "Theros Promos",
    "released_at": "2013-09-21"
  },
  "ddl": {
    "name": "Duel Decks: Heroes vs. Monsters",
    "released_at": "2013-09-06"
  },
  "tddl": {
    "name": "Duel Decks: Heroes vs. Monsters Tokens",
    "released_at": "2013-09-06"
  },
  "v13": {
    "name": "From the Vault: Twenty",
    "released_at": "2013-08-23"
  },
  "m14": {
    "name": "Magic 2014",
    "released_at": "2013-07-19"
  },
  "tm14": {
    "name": "Magic 2014 Tokens",
    "released_at": "2013-07-19"
  },
  "pm14": {
    "name": "Magic 2014 Promos",
    "released_at": "2013-07-18"
  },
  "psdc": {
    "name": "San Diego Comic-Con 2013",
    "released_at": "2013-07-18"
  },
  "tmma": {
    "name": "Modern Masters Tokens",
    "released_at": "2013-06-07"
  },
  "mma": {
    "name": "Modern Masters",
    "released_at": "2013-06-07"
  },
  "dgm": {
    "name": "Dragon's Maze",
    "released_at": "2013-05-03"
  },
  "tdgm": {
    "name": "Dragon's Maze Tokens",
    "released_at": "2013-05-03"
  },
  "pdgm": {
    "name": "Dragon's Maze Promos",
    "released_at": "2013-04-27"
  },
  "wmc": {
    "name": "World Magic Cup Qualifiers",
    "released_at": "2013-04-06"
  },
  "ddk": {
    "name": "Duel Decks: Sorin vs. Tibalt",
    "released_at": "2013-03-15"
  },
  "tddk": {
    "name": "Duel Decks: Sorin vs. Tibalt Tokens",
    "released_at": "2013-03-15"
  },
  "gtc": {
    "name": "Gatecrash",
    "released_at": "2013-02-01"
  },
  "tgtc": {
    "name": "Gatecrash Tokens",
    "released_at": "2013-02-01"
  },
  "pgtc": {
    "name": "Gatecrash Promos",
    "released_at": "2013-01-26"
  },
  "pdp14": {
    "name": "Duels of the Planeswalkers 2014 Promos",
    "released_at": "2013-01-01"
  },
  "l13": {
    "name": "League Tokens 2013",
    "released_at": "2013-01-01"
  },
  "f13": {
    "name": "Friday Night Magic 2013",
    "released_at": "2013-01-01"
  },
  "j13": {
    "name": "Judge Gift Cards 2013",
    "released_at": "2013-01-01"
  },
  "ocm1": {
    "name": "Commander's Arsenal Oversized",
    "released_at": "2012-11-02"
  },
  "cm1": {
    "name": "Commander's Arsenal",
    "released_at": "2012-11-02"
  },
  "rtr": {
    "name": "Return to Ravnica",
    "released_at": "2012-10-05"
  },
  "prtr": {
    "name": "Return to Ravnica Promos",
    "released_at": "2012-10-05"
  },
  "trtr": {
    "name": "Return to Ravnica Tokens",
    "released_at": "2012-10-05"
  },
  "tddj": {
    "name": "Duel Decks: Izzet vs. Golgari Tokens",
    "released_at": "2012-09-07"
  },
  "ddj": {
    "name": "Duel Decks: Izzet vs. Golgari",
    "released_at": "2012-09-07"
  },
  "v12": {
    "name": "From the Vault: Realms",
    "released_at": "2012-08-31"
  },
  "tm13": {
    "name": "Magic 2013 Tokens",
    "released_at": "2012-07-13"
  },
  "m13": {
    "name": "Magic 2013",
    "released_at": "2012-07-13"
  },
  "pm13": {
    "name": "Magic 2013 Promos",
    "released_at": "2012-07-12"
  },
  "opc2": {
    "name": "Planechase 2012 Planes",
    "released_at": "2012-06-01"
  },
  "pc2": {
    "name": "Planechase 2012",
    "released_at": "2012-06-01"
  },
  "avr": {
    "name": "Avacyn Restored",
    "released_at": "2012-05-04"
  },
  "tavr": {
    "name": "Avacyn Restored Tokens",
    "released_at": "2012-05-04"
  },
  "phel": {
    "name": "Open the Helvault",
    "released_at": "2012-04-28"
  },
  "pavr": {
    "name": "Avacyn Restored Promos",
    "released_at": "2012-04-28"
  },
  "ddi": {
    "name": "Duel Decks: Venser vs. Koth",
    "released_at": "2012-03-30"
  },
  "tddi": {
    "name": "Duel Decks: Venser vs. Koth Tokens",
    "released_at": "2012-03-30"
  },
  "tdka": {
    "name": "Dark Ascension Tokens",
    "released_at": "2012-02-03"
  },
  "dka": {
    "name": "Dark Ascension",
    "released_at": "2012-02-03"
  },
  "pdka": {
    "name": "Dark Ascension Promos",
    "released_at": "2012-01-28"
  },
  "pw12": {
    "name": "Wizards Play Network 2012",
    "released_at": "2012-01-01"
  },
  "pdp13": {
    "name": "Duels of the Planeswalkers 2013 Promos",
    "released_at": "2012-01-01"
  },
  "pidw": {
    "name": "IDW Comics Inserts",
    "released_at": "2012-01-01"
  },
  "l12": {
    "name": "League Tokens 2012",
    "released_at": "2012-01-01"
  },
  "f12": {
    "name": "Friday Night Magic 2012",
    "released_at": "2012-01-01"
  },
  "j12": {
    "name": "Judge Gift Cards 2012",
    "released_at": "2012-01-01"
  },
  "pd3": {
    "name": "Premium Deck Series: Graveborn",
    "released_at": "2011-11-18"
  },
  "isd": {
    "name": "Innistrad",
    "released_at": "2011-09-30"
  },
  "tisd": {
    "name": "Innistrad Tokens",
    "released_at": "2011-09-30"
  },
  "pisd": {
    "name": "Innistrad Promos",
    "released_at": "2011-09-24"
  },
  "ddh": {
    "name": "Duel Decks: Ajani vs. Nicol Bolas",
    "released_at": "2011-09-02"
  },
  "tddh": {
    "name": "Duel Decks: Ajani vs. Nicol Bolas Tokens",
    "released_at": "2011-09-02"
  },
  "v11": {
    "name": "From the Vault: Legends",
    "released_at": "2011-08-26"
  },
  "tm12": {
    "name": "Magic 2012 Tokens",
    "released_at": "2011-07-15"
  },
  "m12": {
    "name": "Magic 2012",
    "released_at": "2011-07-15"
  },
  "pm12": {
    "name": "Magic 2012 Promos",
    "released_at": "2011-07-14"
  },
  "ocmd": {
    "name": "Commander 2011 Oversized",
    "released_at": "2011-06-17"
  },
  "cmd": {
    "name": "Commander 2011",
    "released_at": "2011-06-17"
  },
  "pcmd": {
    "name": "Commander 2011 Launch Party",
    "released_at": "2011-06-17"
  },
  "td2": {
    "name": "Duel Decks: Mirrodin Pure vs. New Phyrexia",
    "released_at": "2011-05-14"
  },
  "nph": {
    "name": "New Phyrexia",
    "released_at": "2011-05-13"
  },
  "tnph": {
    "name": "New Phyrexia Tokens",
    "released_at": "2011-05-13"
  },
  "pnph": {
    "name": "New Phyrexia Promos",
    "released_at": "2011-05-12"
  },
  "ddg": {
    "name": "Duel Decks: Knights vs. Dragons",
    "released_at": "2011-04-01"
  },
  "tddg": {
    "name": "Duel Decks: Knights vs. Dragons Tokens",
    "released_at": "2011-04-01"
  },
  "tmbs": {
    "name": "Mirrodin Besieged Tokens",
    "released_at": "2011-02-04"
  },
  "mbs": {
    "name": "Mirrodin Besieged",
    "released_at": "2011-02-04"
  },
  "pmbs": {
    "name": "Mirrodin Besieged Promos",
    "released_at": "2011-02-03"
  },
  "me4": {
    "name": "Masters Edition IV",
    "released_at": "2011-01-10"
  },
  "pmps11": {
    "name": "Magic Premiere Shop 2011",
    "released_at": "2011-01-01"
  },
  "pw11": {
    "name": "Wizards Play Network 2011",
    "released_at": "2011-01-01"
  },
  "pdp12": {
    "name": "Duels of the Planeswalkers 2012 Promos",
    "released_at": "2011-01-01"
  },
  "olgc": {
    "name": "Legacy Championship",
    "released_at": "2011-01-01"
  },
  "p11": {
    "name": "Magic Player Rewards 2011",
    "released_at": "2011-01-01"
  },
  "f11": {
    "name": "Friday Night Magic 2011",
    "released_at": "2011-01-01"
  },
  "g11": {
    "name": "Judge Gift Cards 2011",
    "released_at": "2011-01-01"
  },
  "ps11": {
    "name": "Salvat 2011",
    "released_at": "2011-01-01"
  },
  "pd2": {
    "name": "Premium Deck Series: Fire and Lightning",
    "released_at": "2010-11-19"
  },
  "td0": {
    "name": "Magic Online Theme Decks",
    "released_at": "2010-11-08"
  },
  "tsom": {
    "name": "Scars of Mirrodin Tokens",
    "released_at": "2010-10-01"
  },
  "som": {
    "name": "Scars of Mirrodin",
    "released_at": "2010-10-01"
  },
  "psom": {
    "name": "Scars of Mirrodin Promos",
    "released_at": "2010-09-30"
  },
  "ddf": {
    "name": "Duel Decks: Elspeth vs. Tezzeret",
    "released_at": "2010-09-03"
  },
  "tddf": {
    "name": "Duel Decks: Elspeth vs. Tezzeret Tokens",
    "released_at": "2010-09-03"
  },
  "v10": {
    "name": "From the Vault: Relics",
    "released_at": "2010-08-27"
  },
  "m11": {
    "name": "Magic 2011",
    "released_at": "2010-07-16"
  },
  "tm11": {
    "name": "Magic 2011 Tokens",
    "released_at": "2010-07-16"
  },
  "pm11": {
    "name": "Magic 2011 Promos",
    "released_at": "2010-07-15"
  },
  "oarc": {
    "name": "Archenemy Schemes",
    "released_at": "2010-06-18"
  },
  "arc": {
    "name": "Archenemy",
    "released_at": "2010-06-18"
  },
  "dpa": {
    "name": "Duels of the Planeswalkers",
    "released_at": "2010-06-04"
  },
  "proe": {
    "name": "Rise of the Eldrazi Promos",
    "released_at": "2010-04-23"
  },
  "roe": {
    "name": "Rise of the Eldrazi",
    "released_at": "2010-04-23"
  },
  "troe": {
    "name": "Rise of the Eldrazi Tokens",
    "released_at": "2010-04-23"
  },
  "tdde": {
    "name": "Duel Decks: Phyrexia vs. the Coalition Tokens",
    "released_at": "2010-03-19"
  },
  "dde": {
    "name": "Duel Decks: Phyrexia vs. the Coalition",
    "released_at": "2010-03-19"
  },
  "pwwk": {
    "name": "Worldwake Promos",
    "released_at": "2010-02-05"
  },
  "twwk": {
    "name": "Worldwake Tokens",
    "released_at": "2010-02-05"
  },
  "wwk": {
    "name": "Worldwake",
    "released_at": "2010-02-05"
  },
  "pdp10": {
    "name": "Duels of the Planeswalkers 2010 Promos",
    "released_at": "2010-01-01"
  },
  "pmps10": {
    "name": "Magic Premiere Shop 2010",
    "released_at": "2010-01-01"
  },
  "g10": {
    "name": "Judge Gift Cards 2010",
    "released_at": "2010-01-01"
  },
  "f10": {
    "name": "Friday Night Magic 2010",
    "released_at": "2010-01-01"
  },
  "p10": {
    "name": "Magic Player Rewards 2010",
    "released_at": "2010-01-01"
  },
  "h09": {
    "name": "Premium Deck Series: Slivers",
    "released_at": "2009-11-20"
  },
  "ddd": {
    "name": "Duel Decks: Garruk vs. Liliana",
    "released_at": "2009-10-30"
  },
  "tddd": {
    "name": "Duel Decks: Garruk vs. Liliana Tokens",
    "released_at": "2009-10-30"
  },
  "pzen": {
    "name": "Zendikar Promos",
    "released_at": "2009-10-02"
  },
  "zen": {
    "name": "Zendikar",
    "released_at": "2009-10-02"
  },
  "tzen": {
    "name": "Zendikar Tokens",
    "released_at": "2009-10-02"
  },
  "me3": {
    "name": "Masters Edition III",
    "released_at": "2009-09-07"
  },
  "ohop": {
    "name": "Planechase Planes",
    "released_at": "2009-09-04"
  },
  "hop": {
    "name": "Planechase",
    "released_at": "2009-09-04"
  },
  "phop": {
    "name": "Planechase Promos",
    "released_at": "2009-09-04"
  },
  "v09": {
    "name": "From the Vault: Exiled",
    "released_at": "2009-08-28"
  },
  "tm10": {
    "name": "Magic 2010 Tokens",
    "released_at": "2009-07-17"
  },
  "m10": {
    "name": "Magic 2010",
    "released_at": "2009-07-17"
  },
  "pm10": {
    "name": "Magic 2010 Promos",
    "released_at": "2009-07-16"
  },
  "parb": {
    "name": "Alara Reborn Promos",
    "released_at": "2009-04-30"
  },
  "tarb": {
    "name": "Alara Reborn Tokens",
    "released_at": "2009-04-30"
  },
  "arb": {
    "name": "Alara Reborn",
    "released_at": "2009-04-30"
  },
  "ddc": {
    "name": "Duel Decks: Divine vs. Demonic",
    "released_at": "2009-04-10"
  },
  "tddc": {
    "name": "Duel Decks: Divine vs. Demonic Tokens",
    "released_at": "2009-04-10"
  },
  "purl": {
    "name": "URL/Convention Promos",
    "released_at": "2009-02-08"
  },
  "pcon": {
    "name": "Conflux Promos",
    "released_at": "2009-02-06"
  },
  "con": {
    "name": "Conflux",
    "released_at": "2009-02-06"
  },
  "tcon": {
    "name": "Conflux Tokens",
    "released_at": "2009-02-06"
  },
  "pdtp": {
    "name": "Duels of the Planeswalkers 2009 Promos",
    "released_at": "2009-01-01"
  },
  "pmps09": {
    "name": "Magic Premiere Shop 2009",
    "released_at": "2009-01-01"
  },
  "f09": {
    "name": "Friday Night Magic 2009",
    "released_at": "2009-01-01"
  },
  "p09": {
    "name": "Magic Player Rewards 2009",
    "released_at": "2009-01-01"
  },
  "g09": {
    "name": "Judge Gift Cards 2009",
    "released_at": "2009-01-01"
  },
  "dd2": {
    "name": "Duel Decks: Jace vs. Chandra",
    "released_at": "2008-11-07"
  },
  "tdd2": {
    "name": "Duel Decks: Jace vs. Chandra Tokens",
    "released_at": "2008-11-07"
  },
  "pala": {
    "name": "Shards of Alara Promos",
    "released_at": "2008-10-03"
  },
  "ala": {
    "name": "Shards of Alara",
    "released_at": "2008-10-03"
  },
  "tala": {
    "name": "Shards of Alara Tokens",
    "released_at": "2008-10-03"
  },
  "me2": {
    "name": "Masters Edition II",
    "released_at": "2008-09-22"
  },
  "drb": {
    "name": "From the Vault: Dragons",
    "released_at": "2008-08-29"
  },
  "peve": {
    "name": "Eventide Promos",
    "released_at": "2008-07-25"
  },
  "teve": {
    "name": "Eventide Tokens",
    "released_at": "2008-07-25"
  },
  "eve": {
    "name": "Eventide",
    "released_at": "2008-07-25"
  },
  "pshm": {
    "name": "Shadowmoor Promos",
    "released_at": "2008-05-02"
  },
  "tshm": {
    "name": "Shadowmoor Tokens",
    "released_at": "2008-05-02"
  },
  "shm": {
    "name": "Shadowmoor",
    "released_at": "2008-05-02"
  },
  "p15a": {
    "name": "15th Anniversary Cards",
    "released_at": "2008-04-01"
  },
  "pmor": {
    "name": "Morningtide Promos",
    "released_at": "2008-02-01"
  },
  "mor": {
    "name": "Morningtide",
    "released_at": "2008-02-01"
  },
  "tmor": {
    "name": "Morningtide Tokens",
    "released_at": "2008-02-01"
  },
  "pmps08": {
    "name": "Magic Premiere Shop 2008",
    "released_at": "2008-01-01"
  },
  "g08": {
    "name": "Judge Gift Cards 2008",
    "released_at": "2008-01-01"
  },
  "p08": {
    "name": "Magic Player Rewards 2008",
    "released_at": "2008-01-01"
  },
  "f08": {
    "name": "Friday Night Magic 2008",
    "released_at": "2008-01-01"
  },
  "tdd1": {
    "name": "Duel Decks: Elves vs. Goblins Tokens",
    "released_at": "2007-11-16"
  },
  "dd1": {
    "name": "Duel Decks: Elves vs. Goblins",
    "released_at": "2007-11-16"
  },
  "plrw": {
    "name": "Lorwyn Promos",
    "released_at": "2007-10-12"
  },
  "tlrw": {
    "name": "Lorwyn Tokens",
    "released_at": "2007-10-12"
  },
  "lrw": {
    "name": "Lorwyn",
    "released_at": "2007-10-12"
  },
  "me1": {
    "name": "Masters Edition",
    "released_at": "2007-09-10"
  },
  "10e": {
    "name": "Tenth Edition",
    "released_at": "2007-07-13"
  },
  "p10e": {
    "name": "Tenth Edition Promos",
    "released_at": "2007-07-13"
  },
  "t10e": {
    "name": "Tenth Edition Tokens",
    "released_at": "2007-07-13"
  },
  "pfut": {
    "name": "Future Sight Promos",
    "released_at": "2007-05-04"
  },
  "fut": {
    "name": "Future Sight",
    "released_at": "2007-05-04"
  },
  "pgpx": {
    "name": "Grand Prix Promos",
    "released_at": "2007-02-24"
  },
  "ppro": {
    "name": "Pro Tour Promos",
    "released_at": "2007-02-09"
  },
  "pplc": {
    "name": "Planar Chaos Promos",
    "released_at": "2007-02-02"
  },
  "plc": {
    "name": "Planar Chaos",
    "released_at": "2007-02-02"
  },
  "g07": {
    "name": "Judge Gift Cards 2007",
    "released_at": "2007-01-01"
  },
  "f07": {
    "name": "Friday Night Magic 2007",
    "released_at": "2007-01-01"
  },
  "p07": {
    "name": "Magic Player Rewards 2007",
    "released_at": "2007-01-01"
  },
  "pmps07": {
    "name": "Magic Premiere Shop 2007",
    "released_at": "2007-01-01"
  },
  "hho": {
    "name": "Happy Holidays",
    "released_at": "2006-12-31"
  },
  "ptsp": {
    "name": "Time Spiral Promos",
    "released_at": "2006-10-06"
  },
  "tsb": {
    "name": "Time Spiral Timeshifted",
    "released_at": "2006-10-06"
  },
  "tsp": {
    "name": "Time Spiral",
    "released_at": "2006-10-06"
  },
  "pcsp": {
    "name": "Coldsnap Promos",
    "released_at": "2006-07-21"
  },
  "csp": {
    "name": "Coldsnap",
    "released_at": "2006-07-21"
  },
  "cst": {
    "name": "Coldsnap Theme Decks",
    "released_at": "2006-07-21"
  },
  "pdis": {
    "name": "Dissension Promos",
    "released_at": "2006-05-05"
  },
  "dis": {
    "name": "Dissension",
    "released_at": "2006-05-05"
  },
  "pcmp": {
    "name": "Champs and States",
    "released_at": "2006-03-18"
  },
  "pgpt": {
    "name": "Guildpact Promos",
    "released_at": "2006-02-03"
  },
  "gpt": {
    "name": "Guildpact",
    "released_at": "2006-02-03"
  },
  "pmps06": {
    "name": "Magic Premiere Shop 2006",
    "released_at": "2006-01-01"
  },
  "pal06": {
    "name": "Arena League 2006",
    "released_at": "2006-01-01"
  },
  "pjas": {
    "name": "Junior APAC Series",
    "released_at": "2006-01-01"
  },
  "dci": {
    "name": "DCI Promos",
    "released_at": "2006-01-01"
  },
  "g06": {
    "name": "Judge Gift Cards 2006",
    "released_at": "2006-01-01"
  },
  "f06": {
    "name": "Friday Night Magic 2006",
    "released_at": "2006-01-01"
  },
  "phuk": {
    "name": "Hachette UK",
    "released_at": "2006-01-01"
  },
  "p06": {
    "name": "Magic Player Rewards 2006",
    "released_at": "2006-01-01"
  },
  "p2hg": {
    "name": "Two-Headed Giant Tournament",
    "released_at": "2005-12-09"
  },
  "pmps": {
    "name": "Magic Premiere Shop 2005",
    "released_at": "2005-10-07"
  },
  "prav": {
    "name": "Ravnica: City of Guilds Promos",
    "released_at": "2005-10-07"
  },
  "rav": {
    "name": "Ravnica: City of Guilds",
    "released_at": "2005-10-07"
  },
  "psal": {
    "name": "Salvat 2005",
    "released_at": "2005-08-22"
  },
  "p9ed": {
    "name": "Ninth Edition Promos",
    "released_at": "2005-07-29"
  },
  "9ed": {
    "name": "Ninth Edition",
    "released_at": "2005-07-29"
  },
  "psok": {
    "name": "Saviors of Kamigawa Promos",
    "released_at": "2005-06-03"
  },
  "sok": {
    "name": "Saviors of Kamigawa",
    "released_at": "2005-06-03"
  },
  "pbok": {
    "name": "Betrayers of Kamigawa Promos",
    "released_at": "2005-02-04"
  },
  "bok": {
    "name": "Betrayers of Kamigawa",
    "released_at": "2005-02-04"
  },
  "pal05": {
    "name": "Arena League 2005",
    "released_at": "2005-01-01"
  },
  "pjse": {
    "name": "Junior Series Europe",
    "released_at": "2005-01-01"
  },
  "p05": {
    "name": "Magic Player Rewards 2005",
    "released_at": "2005-01-01"
  },
  "f05": {
    "name": "Friday Night Magic 2005",
    "released_at": "2005-01-01"
  },
  "g05": {
    "name": "Judge Gift Cards 2005",
    "released_at": "2005-01-01"
  },
  "punh": {
    "name": "Unhinged Promos",
    "released_at": "2004-11-19"
  },
  "unh": {
    "name": "Unhinged",
    "released_at": "2004-11-19"
  },
  "pchk": {
    "name": "Champions of Kamigawa Promos",
    "released_at": "2004-10-01"
  },
  "chk": {
    "name": "Champions of Kamigawa",
    "released_at": "2004-10-01"
  },
  "wc04": {
    "name": "World Championship Decks 2004",
    "released_at": "2004-09-01"
  },
  "p5dn": {
    "name": "Fifth Dawn Promos",
    "released_at": "2004-06-04"
  },
  "pmrd": {
    "name": "Mirrodin Promos",
    "released_at": "2004-06-04"
  },
  "5dn": {
    "name": "Fifth Dawn",
    "released_at": "2004-06-04"
  },
  "pdst": {
    "name": "Darksteel Promos",
    "released_at": "2004-02-06"
  },
  "dst": {
    "name": "Darksteel",
    "released_at": "2004-02-06"
  },
  "pal04": {
    "name": "Arena League 2004",
    "released_at": "2004-01-01"
  },
  "g04": {
    "name": "Judge Gift Cards 2004",
    "released_at": "2004-01-01"
  },
  "f04": {
    "name": "Friday Night Magic 2004",
    "released_at": "2004-01-01"
  },
  "p04": {
    "name": "Magic Player Rewards 2004",
    "released_at": "2004-01-01"
  },
  "mrd": {
    "name": "Mirrodin",
    "released_at": "2003-10-02"
  },
  "wc03": {
    "name": "World Championship Decks 2003",
    "released_at": "2003-08-06"
  },
  "p8ed": {
    "name": "Eighth Edition Promos",
    "released_at": "2003-07-28"
  },
  "8ed": {
    "name": "Eighth Edition",
    "released_at": "2003-07-28"
  },
  "pscg": {
    "name": "Scourge Promos",
    "released_at": "2003-05-26"
  },
  "scg": {
    "name": "Scourge",
    "released_at": "2003-05-26"
  },
  "plgn": {
    "name": "Legions Promos",
    "released_at": "2003-02-03"
  },
  "lgn": {
    "name": "Legions",
    "released_at": "2003-02-03"
  },
  "pmoa": {
    "name": "Magic Online Avatars",
    "released_at": "2003-01-01"
  },
  "pjjt": {
    "name": "Japan Junior Tournament",
    "released_at": "2003-01-01"
  },
  "pal03": {
    "name": "Arena League 2003",
    "released_at": "2003-01-01"
  },
  "f03": {
    "name": "Friday Night Magic 2003",
    "released_at": "2003-01-01"
  },
  "ovnt": {
    "name": "Vintage Championship",
    "released_at": "2003-01-01"
  },
  "g03": {
    "name": "Judge Gift Cards 2003",
    "released_at": "2003-01-01"
  },
  "p03": {
    "name": "Magic Player Rewards 2003",
    "released_at": "2003-01-01"
  },
  "wc02": {
    "name": "World Championship Decks 2002",
    "released_at": "2002-12-01"
  },
  "ons": {
    "name": "Onslaught",
    "released_at": "2002-10-07"
  },
  "pons": {
    "name": "Onslaught Promos",
    "released_at": "2002-09-28"
  },
  "jp1": {
    "name": "Hobby Japan Promos",
    "released_at": "2002-07-01"
  },
  "prm": {
    "name": "Magic Online Promos",
    "released_at": "2002-06-24"
  },
  "pjud": {
    "name": "Judgment Promos",
    "released_at": "2002-05-27"
  },
  "jud": {
    "name": "Judgment",
    "released_at": "2002-05-27"
  },
  "ptor": {
    "name": "Torment Promos",
    "released_at": "2002-02-04"
  },
  "tor": {
    "name": "Torment",
    "released_at": "2002-02-04"
  },
  "pal02": {
    "name": "Arena League 2002",
    "released_at": "2002-01-01"
  },
  "g02": {
    "name": "Judge Gift Cards 2002",
    "released_at": "2002-01-01"
  },
  "pr2": {
    "name": "Magic Player Rewards 2002",
    "released_at": "2002-01-01"
  },
  "f02": {
    "name": "Friday Night Magic 2002",
    "released_at": "2002-01-01"
  },
  "dkm": {
    "name": "Deckmasters",
    "released_at": "2001-12-01"
  },
  "pody": {
    "name": "Odyssey Promos",
    "released_at": "2001-10-01"
  },
  "ody": {
    "name": "Odyssey",
    "released_at": "2001-10-01"
  },
  "wc01": {
    "name": "World Championship Decks 2001",
    "released_at": "2001-08-08"
  },
  "psdg": {
    "name": "Sega Dreamcast Cards",
    "released_at": "2001-06-28"
  },
  "papc": {
    "name": "Apocalypse Promos",
    "released_at": "2001-06-04"
  },
  "apc": {
    "name": "Apocalypse",
    "released_at": "2001-06-04"
  },
  "7ed": {
    "name": "Seventh Edition",
    "released_at": "2001-04-11"
  },
  "ppls": {
    "name": "Planeshift Promos",
    "released_at": "2001-02-05"
  },
  "pls": {
    "name": "Planeshift",
    "released_at": "2001-02-05"
  },
  "pal01": {
    "name": "Arena League 2001",
    "released_at": "2001-01-01"
  },
  "mpr": {
    "name": "Magic Player Rewards 2001",
    "released_at": "2001-01-01"
  },
  "g01": {
    "name": "Judge Gift Cards 2001",
    "released_at": "2001-01-01"
  },
  "f01": {
    "name": "Friday Night Magic 2001",
    "released_at": "2001-01-01"
  },
  "pinv": {
    "name": "Invasion Promos",
    "released_at": "2000-10-02"
  },
  "inv": {
    "name": "Invasion",
    "released_at": "2000-10-02"
  },
  "btd": {
    "name": "Beatdown Box Set",
    "released_at": "2000-10-01"
  },
  "wc00": {
    "name": "World Championship Decks 2000",
    "released_at": "2000-08-02"
  },
  "ppcy": {
    "name": "Prophecy Promos",
    "released_at": "2000-06-05"
  },
  "pcy": {
    "name": "Prophecy",
    "released_at": "2000-06-05"
  },
  "s00": {
    "name": "Starter 2000",
    "released_at": "2000-04-01"
  },
  "pnem": {
    "name": "Nemesis Promos",
    "released_at": "2000-02-14"
  },
  "nem": {
    "name": "Nemesis",
    "released_at": "2000-02-14"
  },
  "pelp": {
    "name": "European Land Program",
    "released_at": "2000-02-05"
  },
  "pal00": {
    "name": "Arena League 2000",
    "released_at": "2000-01-01"
  },
  "fnm": {
    "name": "Friday Night Magic 2000",
    "released_at": "2000-01-01"
  },
  "g00": {
    "name": "Judge Gift Cards 2000",
    "released_at": "2000-01-01"
  },
  "psus": {
    "name": "Junior Super Series",
    "released_at": "1999-12-01"
  },
  "brb": {
    "name": "Battle Royale Box Set",
    "released_at": "1999-11-12"
  },
  "pmmq": {
    "name": "Mercadian Masques Promos",
    "released_at": "1999-10-04"
  },
  "mmq": {
    "name": "Mercadian Masques",
    "released_at": "1999-10-04"
  },
  "pwos": {
    "name": "Wizards of the Coast Online Store",
    "released_at": "1999-09-04"
  },
  "wc99": {
    "name": "World Championship Decks 1999",
    "released_at": "1999-08-04"
  },
  "pwor": {
    "name": "World Championship Promos",
    "released_at": "1999-08-04"
  },
  "pgru": {
    "name": "Guru",
    "released_at": "1999-07-12"
  },
  "s99": {
    "name": "Starter 1999",
    "released_at": "1999-07-01"
  },
  "puds": {
    "name": "Urza's Destiny Promos",
    "released_at": "1999-06-07"
  },
  "uds": {
    "name": "Urza's Destiny",
    "released_at": "1999-06-07"
  },
  "pptk": {
    "name": "Portal Three Kingdoms Promos",
    "released_at": "1999-05-01"
  },
  "ptk": {
    "name": "Portal Three Kingdoms",
    "released_at": "1999-05-01"
  },
  "6ed": {
    "name": "Classic Sixth Edition",
    "released_at": "1999-04-21"
  },
  "pulg": {
    "name": "Urza's Legacy Promos",
    "released_at": "1999-02-15"
  },
  "ulg": {
    "name": "Urza's Legacy",
    "released_at": "1999-02-15"
  },
  "pal99": {
    "name": "Arena League 1999",
    "released_at": "1999-01-01"
  },
  "g99": {
    "name": "Judge Gift Cards 1999",
    "released_at": "1999-01-01"
  },
  "ath": {
    "name": "Anthologies",
    "released_at": "1998-11-01"
  },
  "pusg": {
    "name": "Urza's Saga Promos",
    "released_at": "1998-10-12"
  },
  "usg": {
    "name": "Urza's Saga",
    "released_at": "1998-10-12"
  },
  "palp": {
    "name": "Asia Pacific Land Program",
    "released_at": "1998-09-01"
  },
  "wc98": {
    "name": "World Championship Decks 1998",
    "released_at": "1998-08-12"
  },
  "tugl": {
    "name": "Unglued Tokens",
    "released_at": "1998-08-11"
  },
  "ugl": {
    "name": "Unglued",
    "released_at": "1998-08-11"
  },
  "p02": {
    "name": "Portal Second Age",
    "released_at": "1998-06-24"
  },
  "pexo": {
    "name": "Exodus Promos",
    "released_at": "1998-06-15"
  },
  "exo": {
    "name": "Exodus",
    "released_at": "1998-06-15"
  },
  "psth": {
    "name": "Stronghold Promos",
    "released_at": "1998-03-02"
  },
  "sth": {
    "name": "Stronghold",
    "released_at": "1998-03-02"
  },
  "jgp": {
    "name": "Judge Gift Cards 1998",
    "released_at": "1998-01-01"
  },
  "ptmp": {
    "name": "Tempest Promos",
    "released_at": "1997-10-14"
  },
  "tmp": {
    "name": "Tempest",
    "released_at": "1997-10-14"
  },
  "wc97": {
    "name": "World Championship Decks 1997",
    "released_at": "1997-08-13"
  },
  "wth": {
    "name": "Weatherlight",
    "released_at": "1997-06-09"
  },
  "olep": {
    "name": "Oversized League Prizes",
    "released_at": "1997-05-30"
  },
  "pvan": {
    "name": "Vanguard Series",
    "released_at": "1997-05-01"
  },
  "por": {
    "name": "Portal",
    "released_at": "1997-05-01"
  },
  "pmic": {
    "name": "MicroProse Promos",
    "released_at": "1997-04-01"
  },
  "past": {
    "name": "Astral Cards",
    "released_at": "1997-04-01"
  },
  "5ed": {
    "name": "Fifth Edition",
    "released_at": "1997-03-24"
  },
  "vis": {
    "name": "Visions",
    "released_at": "1997-02-03"
  },
  "itp": {
    "name": "Introductory Two-Player Set",
    "released_at": "1996-12-31"
  },
  "mgb": {
    "name": "Multiverse Gift Box",
    "released_at": "1996-11-01"
  },
  "mir": {
    "name": "Mirage",
    "released_at": "1996-10-08"
  },
  "pred": {
    "name": "Redemption Program",
    "released_at": "1996-10-01"
  },
  "pcel": {
    "name": "Celebration Cards",
    "released_at": "1996-08-14"
  },
  "parl": {
    "name": "Arena League 1996",
    "released_at": "1996-08-02"
  },
  "plgm": {
    "name": "DCI Legend Membership",
    "released_at": "1996-07-01"
  },
  "rqs": {
    "name": "Rivals Quick Start Set",
    "released_at": "1996-07-01"
  },
  "all": {
    "name": "Alliances",
    "released_at": "1996-06-10"
  },
  "ptc": {
    "name": "Pro Tour Collector Set",
    "released_at": "1996-05-01"
  },
  "o90p": {
    "name": "Oversized 90's Promos",
    "released_at": "1996-04-01"
  },
  "hml": {
    "name": "Homelands",
    "released_at": "1995-10-01"
  },
  "ren": {
    "name": "Renaissance",
    "released_at": "1995-08-01"
  },
  "rin": {
    "name": "Rinascimento",
    "released_at": "1995-08-01"
  },
  "chr": {
    "name": "Chronicles",
    "released_at": "1995-07-01"
  },
  "bchr": {
    "name": "Chronicles Foreign Black Border",
    "released_at": "1995-07-01"
  },
  "ice": {
    "name": "Ice Age",
    "released_at": "1995-06-03"
  },
  "4bb": {
    "name": "Fourth Edition Foreign Black Border",
    "released_at": "1995-04-01"
  },
  "4ed": {
    "name": "Fourth Edition",
    "released_at": "1995-04-01"
  },
  "pmei": {
    "name": "Media and Collaboration Promos",
    "released_at": "1995-01-01"
  },
  "fem": {
    "name": "Fallen Empires",
    "released_at": "1994-11-01"
  },
  "phpr": {
    "name": "HarperPrism Book Promos",
    "released_at": "1994-09-01"
  },
  "drk": {
    "name": "The Dark",
    "released_at": "1994-08-01"
  },
  "pdrc": {
    "name": "Dragon Con",
    "released_at": "1994-07-15"
  },
  "sum": {
    "name": "Summer Magic / Edgar",
    "released_at": "1994-06-21"
  },
  "leg": {
    "name": "Legends",
    "released_at": "1994-06-01"
  },
  "3ed": {
    "name": "Revised Edition",
    "released_at": "1994-04-11"
  },
  "fbb": {
    "name": "Foreign Black Border",
    "released_at": "1994-04-11"
  },
  "atq": {
    "name": "Antiquities",
    "released_at": "1994-03-04"
  },
  "arn": {
    "name": "Arabian Nights",
    "released_at": "1993-12-17"
  },
  "cei": {
    "name": "Intl. Collectors' Edition",
    "released_at": "1993-12-10"
  },
  "ced": {
    "name": "Collectors' Edition",
    "released_at": "1993-12-10"
  },
  "2ed": {
    "name": "Unlimited Edition",
    "released_at": "1993-12-01"
  },
  "leb": {
    "name": "Limited Edition Beta",
    "released_at": "1993-10-04"
  },
  "lea": {
    "name": "Limited Edition Alpha",
    "released_at": "1993-08-05"
  }
}